Workbook
Name Comprar: [1]Param!#REF!
Name Início_do_projeto: '[2]Gráfico de Gantt'!$G$5
Name Início_do_projeto: 'Gráfico de Gantt'!$G$5
Name Periodicidade: [3]Param!$AB$5:$AB$9
Name Semana_de_exibição: '[2]Gráfico de Gantt'!$G$6
Name Semana_de_exibição: 'Gráfico de Gantt'!$G$6
Name Status: [1]Param!#REF!
Name VersaoExcel: [3]Param!$D$15:$E$15
Name VersaoSR: [3]Param!$C$24:$C$26

Sheet Project Charter

Sheet WBS-MACRO-ATIVIDADE

Sheet WBS_Detalhado (ordem etapas)
B7: 4.1 Plano de ação detalhado da WBS (com dependência, tempo e recurso)
B9: Ref | C9: Etapas – Atividades - | D9: Dependência | E9: Data de inicio | F9: Data final | G9: Duração em dias | H9: Responsável | I9: Recursos | J9: Custos | K9: Obs
B10: 1 | C10: Iniciação e planejamento
B11: 1.1 | C11: Iniciação | D11: - | E11: 46069 | F11: 46076 | G11: =F11-E11 -> 7 | H11: - | I11: - | J11: =SUM(J12:J14) -> 8000
B12: 1.1.1 | C12: Definição do objetivo | D12: 1.1 | E12: 46069 | F12: 46071 | G12: =F12-E12 -> 2 | H12: Henrique Jorge Martins Figueiredo | I12: Pessoas | J12: 2000
B13: 1.1.2 | C13: Alinhamento Estratégico | D13: 1.1 | E13: 46072 | F13: 46073 | G13: =F13-E13 -> 1 | H13: Henrique Jorge Martins Figueiredo | I13: Pessoas | J13: 2000
B14: 1.1.3 | C14: Formalização do project charter | D14: 1.1.1, 1.1.2 | E14: 46074 | F14: 46076 | G14: =F14-E14 -> 2 | H14: Pedro Augusto da Silva Macedo | I14: Pessoas | J14: 4000
B15: 1.2 | C15: Stakeholders | D15: - | E15: 46077 | F15: 46083 | G15: =F15-E15 -> 6 | H15: - | I15: - | J15: 13800
B16: 1.2.1 | C16: Identificação de stakeholders | D16: 1.1.1 | E16: 46077 | F16: 46078 | G16: =F16-E16 -> 1 | H16: Luiz Eduardo Souza Rocha | I16: Pessoas | J16: 800
B17: 1.2.2 | C17: Plano de comunicação com patrocinadores | D17: 1.1.2 | E17: 46079 | F17: 46080 | G17: =F17-E17 -> 1 | H17: Luiz Eduardo Souza Rocha | I17: Pessoas | J17: 2000
B18: 1.2.3 | C18: Gestão de stakeholders | D18: 1.3 | E18: 46083 | F18: 46083 | G18: =F18-E18 -> 0 | H18: Luiz Eduardo Souza Rocha | I18: Pessoas | J18: 11000
B19: 1.3 | C19: Orçamento e Recursos | D19: - | E19: 46084 | F19: 46090 | G19: =F19-E19 -> 6 | H19: - | I19: - | J19: 5700
B20: 1.3.1 | C20: Alocação do investimento | D20: 1.1.3 | E20: 46084 | F20: 46086 | G20: =F20-E20 -> 2 | H20: Pedro Augusto da Silva Macedo | I20: Recursos Próprios | J20: 2500
B21: 1.3.2 | C21: Infraestrutura tecnológica | D21: 1.3.1 | E21: 46087 | F21: 46090 | G21: =F21-E21 -> 3 | H21: Henrique Jorge Martins Figueiredo | I21: Serviços de Nuvem | J21: 3200
B22: 1.4 | C22: Cronograma Detalhado | D22: - | E22: 46091 | F22: 46094 | G22: =F22-E22 -> 3 | H22: - | I22: - | J22: 2500
B23: 1.4.1 | C23: Definição das datas | D23: 1.3.2 | E23: 46091 | F23: 46094 | G23: =F23-E23 -> 3 | H23: Henrique Jorge Martins Figueiredo | I23: Ferramenta de Gestão | J23: 2500
B24: 2 | C24: Levantamento de Requisitos e Dados | J24: =J11+J15+J19+J22 -> 30000
B25: 2.1 | C25: Requisito de Negócios | D25: - | E25: 46097 | F25: 46101 | G25: =F25-E25 -> 4 | H25: - | I25: - | J25: 2500
B26: 2.1.1 | C26: Definição das regras dos planos (Básico, Pro e Premium) | D26: 2.1 | E26: 46097 | F26: 46101 | G26: =F26-E26 -> 4 | H26: Cássio Gonçalves Gama | I26: Pessoas | J26: 2500
B27: 2.2 | C27: Definição de requisitos detalhado | D27: - | E27: 46104 | F27: 46115 | G27: =F27-E27 -> 11 | H27: - | I27: - | J27: 2500
B28: 2.2.1 | C28: Mapeamento de fontes | D28: 2.2 | E28: 46104 | F28: 46108 | G28: =F28-E28 -> 4 | H28: Cássio Gonçalves Gama | I28: Pessoas | J28: 1250
B29: 2.2.2 | C29: Seleção de bases do IBGE, INMET, Segurança pública e receita federal (CNPJ) | D29: 2.2.1 | E29: 46111 | F29: 46115 | G29: =F29-E29 -> 4 | H29: Cássio Gonçalves Gama | I29: Pessoas | J29: 1250
B30: 2.3 | C30: Pipeline de dados | D30: - | E30: 46118 | F30: 46129 | G30: =F30-E30 -> 11 | H30: - | I30: - | J30: =J31+J32+J33 -> 9500
B31: 2.3.1 | C31: Especificação dos processos de coleta | D31: 2.3 | E31: 46118 | F31: 46122 | G31: =F31-E31 -> 4 | H31: Time Técnico | I31: Pessoas | J31: 2500
B32: 2.3.2 | C32: Limpeza | D32: 2.3.1 | E32: 46125 | F32: 46127 | G32: =F32-E32 -> 2 | H32: Time Técnico | I32: Pessoas | J32: 3000
B33: 2.3.3 | C33: Padronização periódica | D33: 2.3.2 | E33: 46128 | F33: 46129 | G33: =F33-E33 -> 1 | H33: Time Técnico | I33: Pessoas | J33: 4000
B34: 3 | C34: Design e experiência do usuário (UX/UI) | J34: =J25+J27+J30 -> 14500
B35: 3.1 | C35: Fluxos de navegação | D35: - | E35: 46132 | F35: 46136 | G35: 5 | H35: - | I35: - | J35: 10000
B36: 3.1.1 | C36: Desenho da jornada para análise de bairros e cidades | D36: 3.1 | E36: 46132 | F36: 46136 | G36: 5 | H36: Renan Damprelli Cardoso da Silva | I36: Pessoas | J36: 10000
B37: 3.2 | C37: Protótipos interativos | D37: - | E37: 46139 | F37: 46150 | G37: 10 | H37: - | I37: - | J37: =J38+J39 -> 8500
B38: 3.2.1 | C38: Criação de telas para dashboards | D38: 3.2 | E38: 46139 | F38: 46143 | G38: 5 | H38: Renan Damprelli Cardoso da Silva | I38: Pessoas | J38: 2500
B39: 3.2.2 | C39: Mapas interativos no figma | D39: 3.2.1 | E39: 46146 | F39: 46150 | G39: 5 | H39: Renan Damprelli Cardoso da Silva | I39: Figma | J39: 6000
B40: 4 | C40: Arquitetura e desenvolvimento técnico | J40: =J35+J37 -> 18500
B41: 4.1 | C41: Estruturação do backend | D41: - | E41: 46153 | F41: 46157 | G41: 5 | H41: - | I41: - | J41: 1500
B42: 4.1.1 | C42: Modelagem do banco de dados territorial centralizado | D42: 4.1 | E42: 46153 | F42: 46157 | G42: 5 | H42: Time Técnico | I42: DB Territorial | J42: 1500
B43: 4.2 | C43: Desenvolvimento frontend | D43: - | E43: 46153 | F43: 46157 | G43: 5 | H43: - | I43: - | J43: 1500
B44: 4.2.1 | C44: Implementação da aplicação Web SaaS respensiva | D44: 4.2 | E44: 46153 | F44: 46157 | G44: 5 | H44: Time Técnico | I44: Nuvem/Hospedagem | J44: 1500
B45: 4.3 | C45: Módulos Analíticos | D45: - | E45: 46160 | F45: 46164 | G45: 5 | H45: - | I45: - | J45: =SUM(J46:J48) -> 10500
B46: 4.3.1 | C46: UrbanScore: Algoritmo de potencial econônomico (0-100) | D46: 4.3 | E46: 46160 | F46: 46161 | G46: 2 | H46: Time Técnico | I46: Modelos Estatísticos | J46: 3500
B47: 4.3.2 | C47: UrbanRisk: Modelo de avaliação de risco territoriais | D47: 4.3 | E47: 46162 | F47: 46163 | G47: 2 | H47: Time Técnico | I47: Modelos Estatísticos | J47: 3500
B48: 4.3.3 | C48: UrbanGrowth: Modelagem estatística de séries temporais para previsões | D48: 4.3 | E48: 46164 | F48: 46164 | G48: 1 | H48: Time Técnico | I48: Modelos Estatísticos | J48: 3500
B49: 4.4 | C49: Relatórios | D49: - | E49: 46167 | F49: 46169 | G49: 3 | H49: - | I49: - | J49: 1000
B50: 4.4.1 | C50: Sistema de exportação de dados | D50: 4.4 | E50: 46167 | F50: 46168 | G50: 2 | H50: Time Técnico | I50: Bibliotecas de Exportação | J50: 500
B51: 4.4.2 | C51: Visualização de graficos | D51: 4.4 | E51: 46169 | F51: 46169 | G51: 1 | H51: Time Técnico | I51: Bibliotecas de Gráficos | J51: 500
B52: 5 | C52: Qualidade, segurança e lançamento | J52: =J41+J43+J45+J49+J53 -> 15000
B53: 5.1 | C53: Segurança e conformidade | D53: - | E53: 46170 | F53: 46176 | G53: 5 | H53: - | I53: - | J53: 500
B54: 5.1.1 | C54: Implementação de autenticação, logs e proteção | D54: 5.1 | E54: 46170 | F54: 46176 | G54: 5 | H54: Time Técnico | I54: Protocolos SSL/Logs | J54: 500
B55: 5.2 | C55: Testes de MVP | D55: - | E55: 46177 | F55: 46183 | G55: 5 | H55: - | I55: - | J55: 1500
B56: 5.2.1 | C56: Validação das funções essenciais | D56: 5.2 | E56: 46177 | F56: 46181 | G56: 3 | H56: Time Técnico | I56: Ambiente de Homologação | J56: 1000
B57: 5.2.2 | C57: Correção de bugs | D57: 5.2.1 | E57: 46182 | F57: 46183 | G57: 2 | H57: Time Técnico | I57: Pessoas | J57: 500
B58: 5.3 | C58: Implantação (Go-Live) | D58: - | E58: 46184 | F58: 46190 | G58: 5 | H58: - | I58: - | J58: 1500
B59: 5.3.1 | C59: Configuração do ambiente de produção em nuvem de baixo custo | D59: 5.3 | E59: 46184 | F59: 46190 | G59: 5 | H59: Time Técnico | I59: Infraestrutura Cloud | J59: 1500
B60: 5.4 | C60: Entrega Final | D60: - | E60: 46191 | F60: 46192 | G60: 2 | H60: - | I60: - | J60: 500
B61: 5.4.1 | C61: Encerramento da fase de desenvolvimento do MVP | D61: 5.4 | E61: 46191 | F61: 46192 | G61: 2 | H61: Henrique Figueiredo | I61: Documentação | J61: 500
B62: 6 | C62: Finalização e Entrega do MVP | J62: =J53+J55+J58+J60 -> 4000
B63: 6.1 | C63: Homologação dos Módulos analíticos | D63: - | E63: 46160 | F63: 46161 | G63: 2 | H63: - | I63: Dados Reais | J63: =J64 -> 6900
B64: 6.1.1 | C64: Validação final dos algoritmos UrbanScore, UrbanRisk e UrbanGrowth com dados reais. | D64: 6.1 | E64: 46160 | F64: 46161 | G64: 2 | H64: Cássio Gonçalves Gama | I64: Pessoas | J64: 6900
B65: 6.2 | C65: Ajustes de UX Baseados em Feedback | D65: - | E65: 46162 | F65: 46163 | G65: 2 | H65: - | I65: Pessoas | J65: =J66 -> 6000
B66: 6.2.1 | C66: Implementação de melhorias rápidas na interface após rodada de testes de usabilidade. | D66: 6.2 | E66: 46162 | F66: 46163 | G66: 2 | H66: Renan Damprelli Cardoso da Silva | I66: Ferramentas Design | J66: 6000
B67: 6.3 | C67: Treinamento e Documentação Técnica | D67: - | E67: 46164 | F67: 46164 | G67: 1 | H67: - | I67: Pessoas | J67: =J68 -> 5000
B68: 6.3.1 | C68: Elaboração de guias de uso da plataforma e documentação da arquitetura do banco de dados. | D68: 6.3 | E68: 46164 | F68: 46164 | G68: 1 | H68: Henrique Jorge Martins Figueiredo | I68: Documentação | J68: 5000
B69: 6.4 | C69: Configuração de Assinaturas e Acessos | D69: - | E69: 46167 | F69: 46168 | G69: 2 | H69: - | I69: Pessoas | J69: =J70 -> 9500
B70: 6.4.1 | C70: Ativação das regras de negócio e controle de uso para os planos Básico, Pro e Premium | D70: 6.4 | E70: 46167 | F70: 46168 | G70: 2 | H70: Pedro Augusto da Silva Macedo | I70: Regras de Assinatura | J70: 9500
B71: 6.5 | C71: Publicação em Ambiente de Produção | D71: - | E71: 46169 | F71: 46169 | G71: 1 | H71: - | I71: Cloud de Baixo Custo | J71: 1000
B72: 6.5.1 | C72: Deploy final da aplicação web em infraestrutura de nuvem de baixo custo | D72: 6.3 | E72: 46169 | F72: 46169 | G72: 1 | H72: Henrique Jorge Martins Figueiredo | I72: Termo de Encerramento | J72: 500
B73: 6.6 | C73: Encerramento do Ciclo de Desenvolvimento | D73: - | E73: 46169 | F73: 46169 | G73: =F73-E73 -> 0 | H73: - | I73: - | J73: -
B74: 6.6.1 | C74: Formalização da entrega da versão funcional (MVP) dentro do prazo estabelecido (27/05/2026) | D74: 6.5.1 | E74: 46169 | F74: 46169 | G74: =F74-E74 -> 0 | H74: - | I74: - | J74: -
J75: =SUM(J63+J65+J67+J69+J71) -> 28400
C76: TOTAL | J76: =SUM(J24+J34+J40+J52+J62+J75) -> 110400

Sheet WBS_Detalhado (ordem depend)
B6: 4.2 Plano de ação detalhado da WBS (com dependência, tempo e recurso)
B8: Ref | C8: Etapas – Atividades - | D8: Dependência | E8: Data de inicio | F8: Data final | G8: Duração em dias | H8: Responsável | I8: Recursos | J8: Obs
B9: 1 | C9: Iniciação e planejamento
B10: 1.1 | C10: Iniciação | D10: - | E10: 46069 | F10: 46076 | G10: 2 | H10: - | I10: -
B11: 1.1.1 | C11: Definição do objetivo | D11: 1.1 | E11: 46069 | F11: 46071 | H11: Henrique Jorge Martins Figueiredo | I11: Pessoas
B12: 1.1.2 | C12: Alinhamento Estratégico | D12: 1.1 | E12: 46072 | F12: 46073 | G12: 1 | H12: Henrique Jorge Martins Figueiredo | I12: Pessoas
B13: 1.1.3 | C13: Formalização do project charter | D13: 1.1.1, 1.1.2 | E13: 46074 | F13: 46076 | G13: 2 | H13: Pedro Augusto da Silva Macedo | I13: Pessoas
B14: 1.2 | C14: Stakeholders | D14: - | E14: 46077 | F14: 46083 | G14: 6 | H14: - | I14: -
B15: 1.2.1 | C15: Identificação de stakeholders | D15: 1.1.1 | E15: 46077 | F15: 46078 | G15: 1 | H15: Luiz Eduardo Souza Rocha | I15: Pessoas
B16: 1.2.2 | C16: Plano de comunicação com patrocinadores | D16: 1.1.2 | E16: 46079 | F16: 46080 | G16: 1 | H16: Luiz Eduardo Souza Rocha | I16: Pessoas
B17: 1.2.3 | C17: Gestão de stakeholders | D17: 1.3 | E17: 46083 | F17: 46083 | G17: 0 | H17: Luiz Eduardo Souza Rocha | I17: Pessoas
B18: 1.3 | C18: Orçamento e Recursos | D18: - | E18: 46084 | F18: 46090 | G18: 6 | H18: - | I18: -
B19: 1.3.1 | C19: Alocação do investimento | D19: 1.1.3 | E19: 46084 | F19: 46086 | G19: 2 | H19: Pedro Augusto da Silva Macedo | I19: Recursos Próprios
B20: 1.3.2 | C20: Infraestrutura tecnológica | D20: 1.3.1 | E20: 46087 | F20: 46090 | G20: 3 | H20: Henrique Jorge Martins Figueiredo | I20: Serviços de Nuvem
B21: 1.4 | C21: Cronograma Detalhado | D21: - | E21: 46091 | F21: 46094 | G21: 3 | H21: - | I21: -
B22: 1.4.1 | C22: Definição das datas | D22: 1.3.2 | E22: 46091 | F22: 46094 | G22: 3 | H22: Henrique Jorge Martins Figueiredo | I22: Ferramenta de Gestão
B23: 2 | C23: Levantamento de Requisitos e Dados
B24: 2.1 | C24: Requisito de Negócios | D24: - | E24: 46097 | F24: 46101 | G24: 4 | H24: - | I24: -
B25: 2.1.1 | C25: Definição das regras dos planos (Básico, Pro e Premium) | D25: 2.1 | E25: 46097 | F25: 46101 | G25: 4 | H25: Cássio Gonçalves Gama | I25: Pessoas
B26: 2.2 | C26: Definição de requisitos detalhado | D26: - | E26: 46104 | F26: 46115 | G26: 11 | H26: - | I26: -
B27: 2.2.1 | C27: Mapeamento de fontes | D27: 2.2 | E27: 46104 | F27: 46108 | G27: 4 | H27: Cássio Gonçalves Gama | I27: Pessoas
B28: 2.2.2 | C28: Seleção de bases do IBGE, INMET, Segurança pública e receita federal (CNPJ) | D28: 2.2.1 | E28: 46111 | F28: 46115 | G28: 4 | H28: Cássio Gonçalves Gama | I28: Pessoas
B29: 2.3 | C29: Pipeline de dados | D29: - | E29: 46118 | F29: 46129 | G29: 11 | H29: - | I29: -
B30: 2.3.1 | C30: Especificação dos processos de coleta | D30: 2.3 | E30: 46118 | F30: 46122 | G30: 4 | H30: Time Técnico | I30: Pessoas
B31: 2.3.2 | C31: Limpeza | D31: 2.3.1 | E31: 46125 | F31: 46127 | G31: 2 | H31: Time Técnico | I31: Pessoas
B32: 2.3.3 | C32: Padronização periódica | D32: 2.3.2 | E32: 46128 | F32: 46129 | G32: 1 | H32: Time Técnico | I32: Pessoas
B33: 3 | C33: Design e experiência do usuário (UX/UI)
B34: 3.1 | C34: Fluxos de navegação | D34: - | E34: 46132 | F34: 46136 | G34: 5 | H34: - | I34: -
B35: 3.1.1 | C35: Desenho da jornada para análise de bairros e cidades | D35: 3.1 | E35: 46132 | F35: 46136 | G35: 5 | H35: Renan Damprelli Cardoso da Silva | I35: Pessoas
B36: 3.2 | C36: Protótipos interativos | D36: - | E36: 46139 | F36: 46150 | G36: 10 | H36: - | I36: -
B37: 3.2.1 | C37: Criação de telas para dashboards | D37: 3.2 | E37: 46139 | F37: 46143 | G37: 5 | H37: Renan Damprelli Cardoso da Silva | I37: Pessoas
B38: 3.2.2 | C38: Mapas interativos no figma | D38: 3.2.1 | E38: 46146 | F38: 46150 | G38: 5 | H38: Renan Damprelli Cardoso da Silva | I38: Figma
B39: 4 | C39: Arquitetura e desenvolvimento técnico
B40: 4.1 | C40: Estruturação do backend | D40: - | E40: 46153 | F40: 46157 | G40: 5 | H40: - | I40: -
B41: 4.1.1 | C41: Modelagem do banco de dados territorial centralizado | D41: 4.1 | E41: 46153 | F41: 46157 | G41: 5 | H41: Time Técnico | I41: DB Territorial
B42: 4.2 | C42: Desenvolvimento frontend | D42: - | E42: 46153 | F42: 46157 | G42: 5 | H42: - | I42: -
B43: 4.2.1 | C43: Implementação da aplicação Web SaaS respensiva | D43: 4.2 | E43: 46153 | F43: 46157 | G43: 5 | H43: Time Técnico | I43: Nuvem/Hospedagem
B44: 4.3 | C44: Módulos Analíticos | D44: - | E44: 46160 | F44: 46164 | G44: 5 | H44: - | I44: -
B45: 4.3.1 | C45: UrbanScore: Algoritmo de potencial econônomico (0-100) | D45: 4.3 | E45: 46160 | F45: 46161 | G45: 2 | H45: Time Técnico | I45: Modelos Estatísticos
B46: 4.3.2 | C46: UrbanRisk: Modelo de avaliação de risco territoriais | D46: 4.3 | E46: 46162 | F46: 46163 | G46: 2 | H46: Time Técnico | I46: Modelos Estatísticos
B47: 4.3.3 | C47: UrbanGrowth: Modelagem estatística de séries temporais para previsões | D47: 4.3 | E47: 46164 | F47: 46164 | G47: 1 | H47: Time Técnico | I47: Modelos Estatísticos
B48: 4.4 | C48: Relatórios | D48: - | E48: 46167 | F48: 46169 | G48: 3 | H48: - | I48: -
B49: 4.4.1 | C49: Sistema de exportação de dados | D49: 4.4 | E49: 46167 | F49: 46168 | G49: 2 | H49: Time Técnico | I49: Bibliotecas de Exportação
B50: 4.4.2 | C50: Visualização de graficos | D50: 4.4 | E50: 46169 | F50: 46169 | G50: 1 | H50: Time Técnico | I50: Bibliotecas de Gráficos
B51: 5 | C51: Qualidade, segurança e lançamento
B52: 5.1 | C52: Segurança e conformidade | D52: - | E52: 46170 | F52: 46176 | G52: 5 | H52: - | I52: -
B53: 5.1.1 | C53: Implementação de autenticação, logs e proteção | D53: 5.1 | E53: 46170 | F53: 46176 | G53: 5 | H53: Time Técnico | I53: Protocolos SSL/Logs
B54: 5.2 | C54: Testes de MVP | D54: - | E54: 46177 | F54: 46183 | G54: 5 | H54: - | I54: -
B55: 5.2.1 | C55: Validação das funções essenciais | D55: 5.2 | E55: 46177 | F55: 46181 | G55: 3 | H55: Time Técnico | I55: Ambiente de Homologação
B56: 5.2.2 | C56: Correção de bugs | D56: 5.2.1 | E56: 46182 | F56: 46183 | G56: 2 | H56: Time Técnico | I56: Pessoas
B57: 5.3 | C57: Implantação (Go-Live) | D57: - | E57: 46184 | F57: 46190 | G57: 5 | H57: - | I57: -
B58: 5.3.1 | C58: Configuração do ambiente de produção em nuvem de baixo custo | D58: 5.3 | E58: 46184 | F58: 46190 | G58: 5 | H58: Time Técnico | I58: Infraestrutura Cloud
B59: 5.4 | C59: Entrega Final | D59: - | E59: 46191 | F59: 46192 | G59: 2 | H59: - | I59: -
B60: 5.4.1 | C60: Encerramento da fase de desenvolvimento do MVP | D60: 5.4 | E60: 46191 | F60: 46192 | G60: 2 | H60: Henrique Figueiredo | I60: Documentação
B61: 6 | C61: Finalização e Entrega do MVP
B62: 6.1 | C62: Homologação dos Módulos analíticos | D62: - | E62: 46160 | F62: 46161 | G62: 2 | H62: - | I62: Dados Reais
B63: 6.1.1 | C63: Validação final dos algoritmos UrbanScore, UrbanRisk e UrbanGrowth com dados reais. | D63: 6.1 | E63: 46160 | F63: 46161 | G63: 2 | H63: Cássio Gonçalves Gama | I63: Pessoas
B64: 6.2 | C64: Ajustes de UX Baseados em Feedback | D64: - | E64: 46162 | F64: 46163 | G64: 2 | H64: - | I64: Pessoas
B65: 6.2.1 | C65: Implementação de melhorias rápidas na interface após rodada de testes de usabilidade. | D65: 6.2 | E65: 46162 | F65: 46163 | G65: 2 | H65: Renan Damprelli Cardoso da Silva | I65: Ferramentas Design
B66: 6.3 | C66: Treinamento e Documentação Técnica | D66: - | E66: 46164 | F66: 46164 | G66: 1 | H66: - | I66: Pessoas
B67: 6.3.1 | C67: Elaboração de guias de uso da plataforma e documentação da arquitetura do banco de dados. | D67: 6.3 | E67: 46164 | F67: 46164 | G67: 1 | H67: Henrique Jorge Martins Figueiredo | I67: Documentação
B68: 6.4 | C68: Configuração de Assinaturas e Acessos | D68: - | E68: 46167 | F68: 46168 | G68: 2 | H68: - | I68: Pessoas
B69: 6.4.1 | C69: Ativação das regras de negócio e controle de uso para os planos Básico, Pro e Premium | D69: 6.4 | E69: 46167 | F69: 46168 | G69: 2 | H69: Pedro Augusto da Silva Macedo | I69: Regras de Assinatura
B70: 6.5 | C70: Publicação em Ambiente de Produção | D70: - | E70: 46169 | F70: 46169 | G70: 1 | H70: - | I70: Cloud de Baixo Custo
B71: 6.5.1 | C71: Deploy final da aplicação web em infraestrutura de nuvem de baixo custo | D71: 6.3 | E71: 46169 | F71: 46169 | G71: 1 | H71: Henrique Jorge Martins Figueiredo | I71: Termo de Encerramento
B72: 6.6 | C72: Encerramento do Ciclo de Desenvolvimento | D72: - | E72: 46169 | F72: 46169 | G72: 0 | H72: - | I72: -
B73: 6.6.1 | C73: Formalização da entrega da versão funcional (MVP) dentro do prazo estabelecido (27/05/2026) | D73: 6.5.1 | E73: 46169 | F73: 46169 | G73: 0 | H73: - | I73: -

Sheet Diagrama de Seta
A1: Projeto para construir uma casa | J1: Diagrama de seta
K2: Atividade fantasma
B3: Quantos Dias dura o projeto?
F4: Dias
A5: Desenvolvimento APP | B5: Atividade | C5: Dependência | D5: Duração | F5: 1 | G5: 2 | H5: 3 | I5: 4 | J5: 5 | K5: 6 | L5: 7 | M5: 8 | N5: 9 | O5: 10 | P5: 11 | Q5: 12 | R5: 13 | S5: 14 | T5: 15 | U5: 16 | V5: 17 | W5: 18 | X5: 19 | Y5: 20 | Z5: 21 | AA5: 22 | AB5: 23 | AC5: 24 | AD5: 25 | AE5: 26 | AF5: 27 | AG5: 28 | AH5: 29 | AI5: 30 | AJ5: 31 | AK5: 32 | AL5: 33 | AM5: 34 | AN5: 35 | AO5: 36 | AP5: 37 | AQ5: 38 | AR5: 39 | AS5: 40 | AT5: 41 | AU5: 42 | AV5: 43 | AW5: 44 | AX5: 45 | AY5: 46 | AZ5: 47 | BA5: 48 | BB5: 49 | BC5: 50 | BD5: 51 | BE5: 52 | BF5: 53 | BG5: 54 | BH5: 55
A6: Definição do objetivo | B6: A | C6: - | D6: 2 | T6: K
A7: Alinhamento estratégico | B7: B | C7: A | D7: 1
A8: Formalização do project charter | B8: C | C8: B | D8: 2 | F8: A | H8: B | I8: C | K8: D | L8: E | P8: H | T8: I | W8: J | AE8: L | AJ8: M
A9: Identificação de stakeholders | B9: D | C9: C | D9: 1
A10: Plano de comunicação | B10: E | C10: D | D10: 1 | AJ10: N | AT10: O | BD10: P
A11: Alocação do investimento | B11: F | C11: C | D11: 2 | K11: F | M11: G
A12: Definição da infraestrutura | B12: G | C12: F | D12: 3
A13: Definição dos planos | B13: H | C13: E, G | D13: 4
A14: Mapeamento das fontes de dados | B14: I | C14: H | D14: 4
A15: Coleta e tratamento dos dados | B15: J | C15: I | D15: 7 | F15: Quantos dias dura o Projeto? 60 dias
A16: Design das telas e dashboards | B16: K | C16: H | D16: 10
A17: Modelagem do banco de dados | B17: L | C17: J | D17: 5 | F17: Quais atividades não podem atrasar?
A18: Desenvolvimento da aplicação SaaS | B18: M | C18: K, L | D18: 15 | F18: A, B, C, F, G, H, I, J, L, M, O, P --> caminho crítico
A19: Criação dos algoritmos | B19: N | C19: J, L | D19: 10
A20: Segurança, testes e correções | B20: O | C20: M, N | D20: 10 | F20: Caminho crítico:
A21: Deploy final e encerramento | B21: P | C21: O | D21: 5 | F21: A → B → C → F → G → H → I → J → L → M → O → P
F23: A atividade D tem folga de 4 dias.
F24: A atividade E tem folga de 4 dias.
F25: A atividade K tem folga de 6 dias.
F26: A atividade N tem folga de 5 dias.

Sheet Diagrama de rede-precedência
A1: Projeto para construir uma casa | G1: PDI -Primeiro dia de início | J1: UDI - Último dia de início
G2: PDT - Primeito dia de término | J2: UDT - Último dia de término
B3: Quantos Dias dura o projeto? | G3: FL-Folgas Livres | J3: 0 | K3: É o caminho crítico
G4: FT-Folgas totais
A6: descrição | B6: Atividade | C6: Dependência | D6: Duração | F6: modelo
A7: Definição do objetivo | B7: A | C7: - | D7: 2 | F7: atividade | G7: duração
A8: Alinhamento estratégico | B8: B | C8: A | D8: 1 | F8: PDI | G8: PDT
A9: Formalização do project charter | B9: C | C9: B | D9: 2 | F9: UDI | G9: UDT | AH9: N | AI9: 10
A10: Identificação de stakeholders | B10: D | C10: C | D10: 1 | F10: FL | G10: FT | AH10: =AF16 -> 30 | AI10: =AH10+AI9 -> 40
A11: Plano de comunicação | B11: E | C11: D | D11: 1 | AH11: =AI11-AI9 -> 35 | AI11: =AK17 -> 45
A12: Alocação do investimento | B12: F | C12: C | D12: 2 | AH12: =AH10-AH11 -> -5 | AI12: =AI10-AI11 -> -5
A13: Definição da infraestrutura | B13: G | C13: F | D13: 3 | F13: A | G13: 2 | I13: B | J13: 1 | L13: C | M13: 2 | O13: D | P13: 1 | R13: E | S13: 1
A14: Definição dos planos | B14: H | C14: E, G | D14: 4 | F14: 0 | G14: 2 | I14: =G14 -> 2 | J14: =I14+J13 -> 3 | L14: =J14 -> 3 | M14: =L14+M13 -> 5 | O14: =M14 -> 5 | P14: =O14+P13 -> 6 | R14: =P14 -> 6 | S14: =R14+S13 -> 7
A15: Mapeamento das fontes de dados | B15: I | C15: H | D15: 4 | F15: =G13-G15 -> 6 | G15: =MIN(AO17,I15,AK17) -> -4 | I15: =J15-J13 -> -4 | J15: =L15 -> -3 | L15: =M13-M15 -> -3 | M15: =MIN(O21,O15) -> 5 | O15: =P15-P13 -> 8 | P15: =R15 -> 9 | R15: =S15-S13 -> 9 | S15: =U17 -> 10 | U15: H | V15: 4 | X15: I | Y15: 4 | AA15: J | AB15: 7 | AE15: L | AF15: 5 | AK15: O | AL15: 10 | AO15: P | AP15: 5
A16: Coleta e tratamento dos dados | B16: J | C16: I | D16: 7 | F16: =F15-F14 -> 6 | G16: =G14-G15 -> 6 | I16: =I14-I15 -> 6 | J16: =J14-J15 -> 6 | L16: =L14-L15 -> 6 | M16: =M14-M15 -> 0 | O16: =O14-O15 -> -3 | P16: =P14-P15 -> -3 | R16: =R14-R15 -> -3 | S16: =S14-S15 -> -3 | U16: =MAX(S14,S20) -> 10 | V16: =U16+V15 -> 14 | X16: =V16 -> 14 | Y16: =X16+Y15 -> 18 | AA16: =Y16 -> 18 | AB16: =AA16+AB15 -> 25 | AE16: =AB16 -> 25 | AF16: =AE16+AF15 -> 30 | AK16: =MAX(AI10,AI23) -> 45 | AL16: =AK16+AL15 -> 55 | AO16: =AL16 -> 55 | AP16: =AO16+AP15 -> 60
A17: Design das telas e dashboards | B17: K | C17: H | D17: 10 | U17: =V17-V15 -> 10 | V17: =MIN(X17,X24) -> 14 | X17: =Y17-Y15 -> 14 | Y17: =AA17 -> 18 | AA17: =AB17-AB15 -> 18 | AB17: =MIN(AE17,AH11) -> 25 | AE17: =AF17-AF15 -> 25 | AF17: =MIN(AH24,AH11) -> 30 | AK17: =AL17-AL15 -> 45 | AL17: =AO17 -> 55 | AO17: =AP17-AP15 -> 55 | AP17: =AP16 -> 60
A18: Modelagem do banco de dados | B18: L | C18: J | D18: 5 | U18: =U16-U17 -> 0 | V18: =V16-V17 -> 0 | X18: =X16-X17 -> 0 | Y18: =Y16-Y17 -> 0 | AA18: =AA16-AA17 -> 0 | AB18: =AB16-AB17 -> 0 | AE18: =AE16-AE17 -> 0 | AF18: =AF16-AF17 -> 0 | AK18: =AK17-AK16 -> 0 | AL18: =AL16-AL17 -> 0 | AO18: =AO16-AO17 -> 0 | AP18: =AP16-AP17 -> 0
A19: Desenvolvimento da aplicação SaaS | B19: M | C19: K, L | D19: 15 | O19: F | P19: 2 | R19: G | S19: 3
A20: Criação dos algoritmos | B20: N | C20: J, L | D20: 10 | O20: =M14 -> 5 | P20: =O20+P19 -> 7 | R20: =P20 -> 7 | S20: =R20+S19 -> 10
A21: Segurança, testes e correções | B21: O | C21: M, N | D21: 10 | O21: =P21-P19 -> 5 | P21: =R21 -> 7 | R21: =S21-S19 -> 7 | S21: =U17 -> 10
A22: Deploy final e encerramento | B22: P | C22: O | D22: 5 | O22: =O20-O21 -> 0 | P22: =P20-P21 -> 0 | R22: =R20-R21 -> 0 | S22: =S20-S21 -> 0 | X22: K | Y22: 10 | AH22: M | AI22: 15
X23: =V16 -> 14 | Y23: =X23+Y22 -> 24 | AH23: =MAX(Y23,AF16) -> 30 | AI23: =AH23+AI22 -> 45
X24: =Y24-Y22 -> 20 | Y24: =AH24 -> 30 | AH24: =AI24-AI22 -> 30 | AI24: =AK17 -> 45
X25: =X24-X23 -> 6 | Y25: =Y24-Y23 -> 6 | AH25: =AH24-AH23 -> 0 | AI25: =AI24-AI23 -> 0

Sheet Plano de Comunicação
A1: 1. Identificação das principais partes interessadas no projeto (stakeholders do projeto)
A3: Quadro 01. Matriz Interesse versus Poder para o projeto
A5: Identificação Stakeholder | B5: Nível de Interesse no projeto | C5: Nível de poder no projeto | D5: Explicar a ação a ser tomada: | G5: Plano de Comunicação
A6: Cliente / Usuários Finais | B6: Utilizar a plataforma para analisar bairros e cidades de forma simples. | C6: Influenciam o sucesso da plataforma pelo uso e feedback. | D6: Usar o sistema, testar os dashboards e informar melhorias necessárias. | G6: Data: 06/05/2026 Projeto: UrbanScore
A7: Product Owner | B7: Garantir que o produto atenda ao objetivo do projeto e tenha valor no mercado. | C7: Define prioridades, funcionalidades e regras dos planos. | D7: Organizar as demandas, priorizar recursos e acompanhar a entrega do MVP.
A8: Gerente do Projeto | B8: Cumprir prazo, custo e escopo planejado. | C8: Controla o andamento das atividades e decisões do projeto. | D8: Acompanhar cronograma, custos, riscos e comunicação com a equipe. | G8: Ref | H8: Atividade | I8: Assunto/Conteúdo | J8: Tipo | K8: Emissor –responsavel | L8: Local | M8: Receptor | N8: Data ou Freqüência | O8: Feedback | P8: Data Feedback | Q8: Obs
A9: Desenvolvedores | B9: Criar a aplicação Web SaaS e corrigir problemas técnicos. | C9: Impactam diretamente a qualidade e funcionamento do sistema. | D9: Programar telas, integrar funcionalidades, corrigir bugs e apoiar o deploy. | G9: STK-001 | H9: Kick-off do Projeto | I9: Apresentação do projeto, objetivos, prazos e principais entregas do MVP. | J9: Reunião | K9: Gerente do Projeto | L9: Meeting online | M9: Equipe do Projeto | N9: Uma vez no início do projeto | O9: Dúvidas e sugestões da equipe | P9: Após a reunião | Q9: Alinhar todos antes de iniciar.
A10: Analista de Dados | B10: Garantir que os dados utilizados sejam corretos e confiáveis. | C10: Influencia diretamente os resultados das análises e algoritmos. | D10: Coletar, limpar, organizar e validar os dados das fontes externas. | G10: STK-002 | H10: Reunião de Planejamento | I10: Definição das atividades, datas, responsáveis e prioridades do projeto. | J10: Reunião | K10: Gerente do Projeto | L10: Meeting online | M10: Product Owner e equipe | N10: Semanalmente | O10: Ajustes no cronograma e tarefas | P10: Após cada reunião | Q10: Acompanhar o andamento do projeto.
A11: Cientista de Dados | B11: Desenvolver os modelos UrbanScore, UrbanRisk e UrbanGrowth. | C11: Tem alto impacto na qualidade das previsões da plataforma. | D11: Criar, testar e ajustar os algoritmos usando dados reais. | G11: STK-003 | H11: Reunião Técnica | I11: Discussão sobre desenvolvimento da aplicação, banco de dados e integrações. | J11: Reunião | K11: Desenvolvedor Líder | L11: Meeting online | M11: Desenvolvedores e DBA | N11: A cada semana | O11: Problemas técnicos encontrados | P11: Após cada reunião | Q11: Evitar atrasos técnicos.
A12: UX/UI Designer | B12: Melhorar a experiência do usuário na plataforma. | C12: Influencia a facilidade de uso e aceitação do sistema. | D12: Criar telas, mapas interativos, dashboards e melhorias visuais. | G12: STK-004 | H12: Validação dos Dados | I12: Conferência das bases do IBGE, INMET, Segurança Pública e Receita Federal. | J12: Reunião | K12: Analista de Dados | L12: Meeting online | M12: Cientista de Dados e Gerente do Projeto | N12: A cada 15 dias | O12: Qualidade e correção dos dados | P12: Após a validação | Q12: Garantir dados confiáveis.
A13: DevOps / Infraestrutura | B13: Manter o sistema funcionando em nuvem. | C13: Tem poder sobre ambiente, deploy, segurança e disponibilidade. | D13: Configurar hospedagem, monitorar servidor, backups e publicação final. | G13: STK-005 | H13: Revisão dos Algoritmos | I13: Avaliação dos modelos UrbanScore, UrbanRisk e UrbanGrowth. | J13: Reunião | K13: Cientista de Dados | L13: Meeting online | M13: Product Owner e equipe técnica | N13: Quinzenalmente | O13: Ajustes nos cálculos e previsões | P13: Após cada teste | Q13: Melhorar a precisão dos resultados.
G14: STK-006 | H14: Revisão de Interface | I14: Avaliação das telas, dashboards, gráficos e mapas interativos. | J14: Reunião | K14: UX/UI Designer | L14: Figma / Meeting | M14: Product Owner e usuários de teste | N14: Semanalmente | O14: Sugestões de melhoria na interface | P14: Após cada teste | Q14: Melhorar a experiência do usuário.
G15: STK-007 | H15: Reunião de Segurança | I15: Verificação de login, autenticação, logs, SSL e proteção do sistema. | J15: Reunião | K15: Analista de Segurança | L15: Meeting online | M15: DevOps e Desenvolvedores | N15: Antes do deploy | O15: Falhas ou melhorias de segurança | P15: Após os testes | Q15: Reduzir riscos de acesso indevido.
G16: STK-008 | H16: Acompanhamento Comercial | I16: Discussão sobre planos Básico, Pro e Premium e regras de uso. | J16: Reunião | K16: Time Comercial | L16: Meeting online | M16: Product Owner e Marketing | N16: A cada 15 dias | O16: Ajustes nas regras dos planos | P16: Após cada reunião | Q16: Preparar o lançamento comercial.
H18: Gerente do projeto: | I18: Pedro Augusto da Silva Macedo | J18: Elaborado por: UrbanScore | N18: Aprovado por: Fecap
G19: Alternativas para o campo Tipo de Mensagem: Relatório executivo, Relatório operacional, Cartilha, Apostila, Prontuário de registros. Arquivo, e-Mail, Correio convencional, Carta registrada, Corrier, Telefone (voice-mail), Fax, Reunião, Apresentação, Workshop, Memorando (de/para), Jornal, Vídeo (filme VHS, AVI, etc), Quadro de avisos, Painel, Lista de discução, Internet ou Intranet, entre outras.

Sheet Orcamento_Previsto
A1: GESTÃO DE CUSTOS – ORÇAMENTO PREVISTO
A2: Projeto: Sistema de Gestão Empresarial | Empresa: ADS Tecnologia
A3: ID | B3: Fase | C3: Tarefa | D3: Dias Estimadas | E3: Custo/Dias (R$) | F3: Custo Previsto (R$) | G3: % do Total
A4: 1.1.1 | B4: Pessoas | C4: Definição do objetivo | D4: 2 | E4: 4000 | F4: =D4*E4 -> 8000 | G4: =IF(F$39=0,0,F4/F$39) -> 0.058415489
A5: 1.1.2 | B5: Pessoas | C5: Alinhamento Estratégico | D5: 1 | E5: 2000 | F5: =D5*E5 -> 2000 | G5: =IF(F$39=0,0,F5/F$39) -> 0.014603872
A6: 1.1.3 | B6: Pessoas | C6: Formalização do project charter | D6: 2 | E6: 1000 | F6: =D6*E6 -> 2000 | G6: =IF(F$39=0,0,F6/F$39) -> 0.014603872
A7: 1.2.1 | B7: Pessoas | C7: Identificação de stakeholders | D7: 1 | E7: 13800 | F7: =D7*E7 -> 13800 | G7: =IF(F$39=0,0,F7/F$39) -> 0.10076672
A8: 1.2.2 | B8: Pessoas | C8: Plano de comunicação com patrocinadores | D8: 1 | E8: 800 | F8: =D8*E8 -> 800 | G8: =IF(F$39=0,0,F8/F$39) -> 0.0058415489
A9: 1.2.3 | B9: Pessoas | C9: Gestão de stakeholders | D9: 1 | E9: 2000 | F9: =D9*E9 -> 2000 | G9: =IF(F$39=0,0,F9/F$39) -> 0.014603872
A10: 1.3.1 | B10: Recursos Próprios | C10: Alocação do investimento | D10: 2 | E10: 2850 | F10: =D10*E10 -> 5700 | G10: =IF(F$39=0,0,F10/F$39) -> 0.041621036
A11: 1.3.2 | B11: Serviços de Nuvem | C11: Infraestrutura tecnológica | D11: 3 | E11: 833.33 | F11: =D11*E11 -> 2499.99 | G11: =IF(F$39=0,0,F11/F$39) -> 0.018254767
A12: 1.4.1 | B12: Ferramenta de Gestão | C12: Definição das datas | D12: 3 | E12: 833.33 | F12: =D12*E12 -> 2499.99 | G12: =IF(F$39=0,0,F12/F$39) -> 0.018254767
A13: 2.1.1 | B13: Pessoas | C13: Definição das regras dos planos (Básico, Pro e Premium) | D13: 4 | E13: 625 | F13: =D13*E13 -> 2500 | G13: =IF(F$39=0,0,F13/F$39) -> 0.01825484
A14: 2.2.1 | B14: Pessoas | C14: Mapeamento de fontes | D14: 4 | E14: 625 | F14: =D14*E14 -> 2500 | G14: =IF(F$39=0,0,F14/F$39) -> 0.01825484
A15: 2.2.2 | B15: Pessoas | C15: Seleção de bases do IBGE, INMET, Segurança pública e receita federal (CNPJ) | D15: 4 | E15: 312.5 | F15: =D15*E15 -> 1250 | G15: =IF(F$39=0,0,F15/F$39) -> 0.0091274201
... A38: 6.5.1 | B38: Termo de Encerramento | C38: Deploy final da aplicação web em infraestrutura de nuvem de baixo custo | D38: 1 | E38: 1000 | F38: =D38*E38 -> 1000 | G38: =IF(F$39=0,0,F38/F$39) -> 0.0073019361
A39: TOTAL DO PROJETO | D39: =SUM(D4:D38) -> 93 | E39: — | F39: =SUM(F4:F38) -> 136949.98 | G39: 100.0%

Sheet Custos_Reais
A1: GESTÃO DE CUSTOS – CUSTOS REAIS APURADOS
A2: Projeto: Sistema de Gestão Empresarial | Empresa: ADS Tecnologia
A3: ID | B3: Fase | C3: Tarefa | D3: Horas Reais | E3: Custo/Hora (R$) | F3: Custo Real (R$) | G3: Status
A4: 1.1.1 | B4: Pessoas | C4: Definição do objetivo | D4: 3 | E4: 4000 | F4: 8000 | G4: =IF(F4>[4]Orcamento_Previsto!F4,"⚠ Acima","✔ OK") -> ✔ OK
A5: 1.1.2 | B5: Pessoas | C5: Alinhamento Estratégico | D5: 1 | E5: 2000 | F5: 2200 | G5: =IF(F5>[4]Orcamento_Previsto!F5,"⚠ Acima","✔ OK") -> ⚠ Acima
A6: 1.1.3 | B6: Pessoas | C6: Formalização do project charter | D6: 2 | E6: 1000 | F6: 1900 | G6: =IF(F6>[4]Orcamento_Previsto!F6,"⚠ Acima","✔ OK") -> ✔ OK
A7: 1.2.1 | B7: Pessoas | C7: Identificação de stakeholders | D7: 1 | E7: 13800 | F7: 13800 | G7: =IF(F7>[4]Orcamento_Previsto!F7,"⚠ Acima","✔ OK") -> ✔ OK
A8: 1.2.2 | B8: Pessoas | C8: Plano de comunicação com patrocinadores | D8: 1 | E8: 800 | F8: 1000 | G8: =IF(F8>[4]Orcamento_Previsto!F8,"⚠ Acima","✔ OK") -> ⚠ Acima
A9: 1.2.3 | B9: Pessoas | C9: Gestão de stakeholders | D9: 1 | E9: 2000 | F9: 1800 | G9: =IF(F9>[4]Orcamento_Previsto!F9,"⚠ Acima","✔ OK") -> ✔ OK
A10: 1.3.1 | B10: Recursos Próprios | C10: Alocação do investimento | D10: 2 | E10: 2850 | F10: 5700 | G10: =IF(F10>[4]Orcamento_Previsto!F10,"⚠ Acima","✔ OK") -> ✔ OK
A11: 1.3.2 | B11: Serviços de Nuvem | C11: Infraestrutura tecnológica | D11: 3 | E11: 833.33 | F11: 2699.99 | G11: =IF(F11>[4]Orcamento_Previsto!F11,"⚠ Acima","✔ OK") -> ⚠ Acima
A12: 1.4.1 | B12: Ferramenta de Gestão | C12: Definição das datas | D12: 3 | E12: 833.33 | F12: 2399.99 | G12: =IF(F12>[4]Orcamento_Previsto!F12,"⚠ Acima","✔ OK") -> ✔ OK
A13: 2.1.1 | B13: Pessoas | C13: Definição das regras dos planos (Básico, Pro e Premium) | D13: 4 | E13: 625 | F13: 2500 | G13: =IF(F13>[4]Orcamento_Previsto!F13,"⚠ Acima","✔ OK") -> ✔ OK
A14: 2.2.1 | B14: Pessoas | C14: Mapeamento de fontes | D14: 4 | E14: 625 | F14: 2300 | G14: =IF(F14>[4]Orcamento_Previsto!F14,"⚠ Acima","✔ OK") -> ✔ OK
A15: 2.2.2 | B15: Pessoas | C15: Seleção de bases do IBGE, INMET, Segurança pública e receita federal (CNPJ) | D15: 4 | E15: 312.5 | F15: 1400 | G15: =IF(F15>[4]Orcamento_Previsto!F15,"⚠ Acima","✔ OK") -> ⚠ Acima
... A38: 6.5.1 | B38: Termo de Encerramento | C38: Deploy final da aplicação web em infraestrutura de nuvem de baixo custo | D38: 1 | E38: 1000 | F38: 1000 | G38: =IF(F38>[4]Orcamento_Previsto!F38,"⚠ Acima","✔ OK") -> ✔ OK
A39: TOTAL DO PROJETO | D39: =SUM(D4:D38) -> 94 | E39: — | F39: =SUM(F4:F38) -> 139831.98 | G39: —

Sheet Analise_Custos
A1: ANÁLISE COMPARATIVA – ORÇADO vs REALIZADO
A2: Projeto: Sistema de Gestão Empresarial | Empresa: ADS Tecnologia
A3: ID | B3: Fase | C3: Tarefa | D3: Previsto (R$) | E3: Real (R$) | F3: Variação (R$) | G3: Variação (%) | H3: Status
A4: 1.1.1 | B4: Pessoas | C4: Definição do objetivo | D4: =Orcamento_Previsto!F4 -> 8000 | E4: =Custos_Reais!F4 -> 8000 | F4: =E4-D4 -> 0 | G4: =IF(D4=0,0,(E4-D4)/D4) -> 0 | H4: =IF(E4>D4,"⚠ Acima","✔ OK") -> ✔ OK
A5: 1.1.2 | B5: Pessoas | C5: Alinhamento Estratégico | D5: =Orcamento_Previsto!F5 -> 2000 | E5: =Custos_Reais!F5 -> 2200 | F5: =E5-D5 -> 200 | G5: =IF(D5=0,0,(E5-D5)/D5) -> 0.1 | H5: =IF(E5>D5,"⚠ Acima","✔ OK") -> ⚠ Acima
A6: 1.1.3 | B6: Pessoas | C6: Formalização do project charter | D6: =Orcamento_Previsto!F6 -> 2000 | E6: =Custos_Reais!F6 -> 1900 | F6: =E6-D6 -> -100 | G6: =IF(D6=0,0,(E6-D6)/D6) -> -0.05 | H6: =IF(E6>D6,"⚠ Acima","✔ OK") -> ✔ OK
A7: 1.2.1 | B7: Pessoas | C7: Identificação de stakeholders | D7: =Orcamento_Previsto!F7 -> 13800 | E7: =Custos_Reais!F7 -> 13800 | F7: =E7-D7 -> 0 | G7: =IF(D7=0,0,(E7-D7)/D7) -> 0 | H7: =IF(E7>D7,"⚠ Acima","✔ OK") -> ✔ OK
A8: 1.2.2 | B8: Pessoas | C8: Plano de comunicação com patrocinadores | D8: =Orcamento_Previsto!F8 -> 800 | E8: =Custos_Reais!F8 -> 1000 | F8: =E8-D8 -> 200 | G8: =IF(D8=0,0,(E8-D8)/D8) -> 0.25 | H8: =IF(E8>D8,"⚠ Acima","✔ OK") -> ⚠ Acima
A9: 1.2.3 | B9: Pessoas | C9: Gestão de stakeholders | D9: =Orcamento_Previsto!F9 -> 2000 | E9: =Custos_Reais!F9 -> 1800 | F9: =E9-D9 -> -200 | G9: =IF(D9=0,0,(E9-D9)/D9) -> -0.1 | H9: =IF(E9>D9,"⚠ Acima","✔ OK") -> ✔ OK
A10: 1.3.1 | B10: Recursos Próprios | C10: Alocação do investimento | D10: =Orcamento_Previsto!F10 -> 5700 | E10: =Custos_Reais!F10 -> 5700 | F10: =E10-D10 -> 0 | G10: =IF(D10=0,0,(E10-D10)/D10) -> 0 | H10: =IF(E10>D10,"⚠ Acima","✔ OK") -> ✔ OK
A11: 1.3.2 | B11: Serviços de Nuvem | C11: Infraestrutura tecnológica | D11: =Orcamento_Previsto!F11 -> 2499.99 | E11: =Custos_Reais!F11 -> 2699.99 | F11: =E11-D11 -> 200 | G11: =IF(D11=0,0,(E11-D11)/D11) -> 0.08000032 | H11: =IF(E11>D11,"⚠ Acima","✔ OK") -> ⚠ Acima
A12: 1.4.1 | B12: Ferramenta de Gestão | C12: Definição das datas | D12: =Orcamento_Previsto!F12 -> 2499.99 | E12: =Custos_Reais!F12 -> 2399.99 | F12: =E12-D12 -> -100 | G12: =IF(D12=0,0,(E12-D12)/D12) -> -0.04000016 | H12: =IF(E12>D12,"⚠ Acima","✔ OK") -> ✔ OK
A13: 2.1.1 | B13: Pessoas | C13: Definição das regras dos planos (Básico, Pro e Premium) | D13: =Orcamento_Previsto!F13 -> 2500 | E13: =Custos_Reais!F13 -> 2500 | F13: =E13-D13 -> 0 | G13: =IF(D13=0,0,(E13-D13)/D13) -> 0 | H13: =IF(E13>D13,"⚠ Acima","✔ OK") -> ✔ OK
A14: 2.2.1 | B14: Pessoas | C14: Mapeamento de fontes | D14: =Orcamento_Previsto!F14 -> 2500 | E14: =Custos_Reais!F14 -> 2300 | F14: =E14-D14 -> -200 | G14: =IF(D14=0,0,(E14-D14)/D14) -> -0.08 | H14: =IF(E14>D14,"⚠ Acima","✔ OK") -> ✔ OK
A15: 2.2.2 | B15: Pessoas | C15: Seleção de bases do IBGE, INMET, Segurança pública e receita federal (CNPJ) | D15: =Orcamento_Previsto!F15 -> 1250 | E15: =Custos_Reais!F15 -> 1400 | F15: =E15-D15 -> 150 | G15: =IF(D15=0,0,(E15-D15)/D15) -> 0.12 | H15: =IF(E15>D15,"⚠ Acima","✔ OK") -> ⚠ Acima
... A38: 6.5.1 | B38: Termo de Encerramento | C38: Deploy final da aplicação web em infraestrutura de nuvem de baixo custo | D38: =Orcamento_Previsto!F38 -> 1000 | E38: =Custos_Reais!F38 -> 1000 | F38: =E38-D38 -> 0 | G38: =IF(D38=0,0,(E38-D38)/D38) -> 0 | H38: =IF(E38>D38,"⚠ Acima","✔ OK") -> ✔ OK
A39: TOTAL DO PROJETO | D39: =SUM(D4:D38) -> 136949.98 | E39: =SUM(E4:E38) -> 139831.98 | F39: =E39-D39 -> 2882 | G39: =IF(D39<>0,(E39-D39)/D39,0) -> 0.02104418 | H39: =IF(E39>D39,"⚠ Acima","✔ OK") -> ⚠ Acima

Sheet Graficos
A1: GRÁFICOS – ORÇADO vs REALIZADO POR TAREFA
A2: Tarefa (resumo) | B2: Previsto (R$) | C2: Real (R$)
A3: Definir objetivo | B3: =Analise_Custos!D4 -> 8000 | C3: =Analise_Custos!E4 -> 8000
A4: Alinhar estratégia | B4: =Analise_Custos!D5 -> 2000 | C4: =Analise_Custos!E5 -> 2200
A5: Formalizar projeto | B5: =Analise_Custos!D6 -> 2000 | C5: =Analise_Custos!E6 -> 1900
A6: Identificar stakeholders | B6: =Analise_Custos!D7 -> 13800 | C6: =Analise_Custos!E7 -> 13800
A7: Comunicar patrocinadores | B7: =Analise_Custos!D8 -> 800 | C7: =Analise_Custos!E8 -> 1000
A8: Gerir stakeholders | B8: =Analise_Custos!D9 -> 2000 | C8: =Analise_Custos!E9 -> 1800
A9: Alocar investimento | B9: =Analise_Custos!D10 -> 5700 | C9: =Analise_Custos!E10 -> 5700
A10: Definir infraestrutura | B10: =Analise_Custos!D11 -> 2499.99 | C10: =Analise_Custos!E11 -> 2699.99
A11: Definir datas | B11: =Analise_Custos!D12 -> 2499.99 | C11: =Analise_Custos!E12 -> 2399.99
A12: Definir planos | B12: =Analise_Custos!D13 -> 2500 | C12: =Analise_Custos!E13 -> 2500
A13: Mapear fontes | B13: =Analise_Custos!D14 -> 2500 | C13: =Analise_Custos!E14 -> 2300
A14: Selecionar bases de dados | B14: =Analise_Custos!D15 -> 1250 | C14: =Analise_Custos!E15 -> 1400
... A37: Fazer deploy final | B37: =Analise_Custos!D38 -> 1000 | C37: =Analise_Custos!E38 -> 1000
A38: RESUMO EXECUTIVO
A39: Total Previsto (R$) | B39: =SUM(B3:B37) -> 136949.98
A40: Total Real (R$) | B40: =SUM(C3:C37) -> 139831.98
A41: Variação Total (R$) | B41: =B40-B39 -> 2882
A42: Variação Total (%) | B42: =IF(B39<>0,(B40-B39)/B39,0) -> 0.02104418
A43: Tarefas Acima do Orçado | B43: =COUNTIF(Analise_Custos!H4:H38,"⚠ Acima") -> 12
A44: Tarefas No Prazo | B44: =COUNTIF(Analise_Custos!H4:H38,"✔ OK") -> 23

Sheet Capa
B5: Informações sobre o projeto
B6: Projeto | E6: UrbanScore
B7: Gerente Responsável | E7: Gerente do projeto
B8: Data da avaliação | E8: dd/mm/aaaa
B9: Histórico da avaliação de riscos
B10: dd/mm/aaaa | C10: Comentário

Sheet Identificar
A1: Identificação dos Riscos | AF1: Probabilidade | AI1: Impacto
A4: =Capa!E6 -> UrbanScore
AF5: Muito Baixa - 1 | AG5: 1 | AI5: Muito Baixo - 1 | AJ5: 1
A6: ID | B6: Fase ou | D6: Declaração do Risco | G6: Resp. | H6: Estratégia de Resposta | I6: Plano de Prevenção | J6: Plano de Contingência | L6: Severidade (X,Y) | AF6: Baixa - 2 | AG6: 2 | AI6: Muito Baixo - 2 | AJ6: 2
B7: Recurso | C7: Classificação | D7: CAUSA (Começa a frase com "Como Resultado ...") | E7: RISCO (Começar a frase com "Pode ocorrer ...") | F7: CONSEQUÊNCIA (Começar a frase com "O que acarretaria ...") | K7: Riscos Colaterais | AF7: Moderada - 3 | AG7: 3 | AI7: Baixo - 3 | AJ7: 3
A8: R01 | B8: API | C8: Instabilidade | D8: Como resultado de falha na API externa | E8: Pode ocorrer queda na comunicação do sistema | F8: Algumas funções podem parar de funcionar | G8: Desenvolvedor Backend | H8: Mitigar | I8: Monitorar a API e testar as integrações | J8: Usar API reserva ou corrigir a integração | K8: Atraso no projeto e aumento nos custos | L8: =Qualificar!K8 -> 0.16 | AF8: Alta - 4 | AG8: 4 | AI8: Baixo - 4 | AJ8: 4
A9: R02 | B9: Servidor | C9: Indisponibilidade | D9: Como resultado de queda no servidor | E9: Pode ocorrer sistema fora do ar | F9: Usuários não conseguirão acessar a plataforma | G9: DevOps / Infraestrutura | H9: Transferir | I9: Contratar servidor confiável e acompanhar disponibilidade | J9: Acionar suporte da hospedagem e subir sistema reserva | L9: =Qualificar!K9 -> 0.32
A10: R03 | B10: Aplicação Web | C10: Bugs | D10: Como resultado de erro no desenvolvimento | E10: Pode ocorrer falha nas funcionalidades | F10: Usuário pode ter dificuldade para usar o sistema | G10: Desenvolvedor Web | H10: Mitigar | I10: Fazer testes durante o desenvolvimento | J10: Corrigir bugs e publicar nova versão | L10: =Qualificar!K10 -> 0.04
A11: R04 | B11: Backup | C11: Falha operacional | D11: Como resultado de backup não realizado corretamente | E11: Pode ocorrer perda de dados importantes | F11: O projeto pode precisar refazer informações | G11: DevOps / Infraestrutura | H11: Evitar | I11: Programar backup automático todos os dias | J11: Restaurar o último backup salvo | L11: =Qualificar!K11 -> 0.02
A12: R05 | B12: Arquivos | C12: Perda de dados | D12: Como resultado de exclusão ou corrupção de arquivos | E12: Pode ocorrer perda de documentos do projeto | F12: A equipe pode ter retrabalho | G12: Gerente do Projeto | H12: Mitigar | I12: Organizar arquivos em nuvem com controle de acesso | J12: Recuperar cópias salvas ou refazer arquivos | L12: =Qualificar!K12 -> 0.02
A13: R06 | B13: Banco de Dados | C13: Erro de conexão | D13: Como resultado de falha na conexão com o banco | E13: Pode ocorrer lentidão ou erro nas consultas | F13: Os dashboards podem não carregar corretamente | G13: DBA / Banco de Dados | H13: Mitigar | I13: Testar conexão e desempenho do banco | J13: Corrigir conexão e reiniciar serviços | L13: =Qualificar!K13 -> 0.08
A14: R07 | B14: Nuvem | C14: Limite de uso | D14: Como resultado do uso de hospedagem de baixo custo | E14: Pode ocorrer falta de recursos no servidor | F14: O sistema pode ficar lento | G14: DevOps / Infraestrutura | H14: Aceitar | I14: Acompanhar limite da hospedagem usada | J14: Aumentar o plano da nuvem se precisar | L14: =Qualificar!K14 -> 0.32
A15: R08 | B15: Segurança | C15: Acesso indevido | D15: Como resultado de senha fraca ou falha de autenticação | E15: Pode ocorrer acesso não autorizado | F15: Informações podem ser expostas | G15: Analista de Segurança | H15: Evitar | I15: Usar senha forte, SSL e controle de acesso | J15: Bloquear acessos suspeitos e trocar senhas | L15: =Qualificar!K15 -> 0.02
A16: R09 | B16: Dados | C16: Dados incorretos | D16: Como resultado de bases desatualizadas ou incompletas | E16: Pode ocorrer análise errada dos bairros e cidades | F16: Os resultados podem perder confiança | G16: Analista de Dados | H16: Mitigar | I16: Conferir a qualidade das bases antes de usar | J16: Atualizar ou trocar a base de dados | L16: =Qualificar!K16 -> 0.08
A17: R10 | B17: Integração | C17: Falha entre sistemas | D17: Como resultado de erro na integração com fontes externas | E17: Pode ocorrer falha na coleta automática | F17: O sistema pode ficar sem dados atualizados | G17: Desenvolvedor Backend | H17: Mitigar | I17: Testar a coleta automática com frequência | J17: Fazer coleta manual até corrigir | L17: =Qualificar!K17 -> 0.32
A18: R11 | B18: Interface | C18: Erro visual | D18: Como resultado de telas mal ajustadas | E18: Pode ocorrer dificuldade de navegação | F18: O usuário pode abandonar a plataforma | G18: Designer UX/UI | H18: Mitigar | I18: Testar as telas com usuários | J18: Ajustar rapidamente as telas com problema | L18: =Qualificar!K18 -> 0.02
A19: R12 | B19: Exportação | C19: Falha no download | D19: Como resultado de erro na função de exportar dados | E19: Pode ocorrer falha ao gerar relatórios | F19: O usuário não conseguirá salvar as análises | G19: Desenvolvedor Web | H19: Mitigar | I19: Testar a exportação antes da entrega | J19: Gerar relatório manual ou corrigir função | L19: =Qualificar!K19 -> 0.08
A20: R13 | B20: Gráficos | C20: Erro de visualização | D20: Como resultado de bug nas bibliotecas de gráficos | E20: Pode ocorrer gráfico incorreto ou não carregado | F20: A análise visual pode ficar prejudicada | G20: Desenvolvedor Frontend | H20: Mitigar | I20: Testar gráficos em diferentes telas | J20: Corrigir biblioteca ou trocar o modelo do gráfico | L20: =Qualificar!K20 -> 0.08
... A23: R16 | B23: Documentação | C23: Falta de registro | D23: Como resultado de documentação incompleta | E23: Pode ocorrer dificuldade para corrigir problemas futuros | F23: A manutenção do sistema ficará mais difícil | G23: Analista de Documentação | H23: Aceitar | I23: Registrar as informações principais do sistema | J23: Completar a documentação depois da entrega | L23: =Qualificar!K23 -> 0.0025

Sheet Qualificar
A1: Qualificação dos Riscos | AF1: Probabilidade | AI1: Impacto
K2: Base Custo | M2: 10000 | N2: R$
K3: Base Prazo | M3: 30 | N3: dias úteis
A4: =[5]Identificar!A4 -> UrbanScore
AF5: Muito Baixa - 1 | AG5: 1 | AI5: Muito Baixo - 1 | AJ5: 1
A6: ID | B6: Declaração do Risco | E6: Resp. | F6: Probabilidade do risco virar incidente (Y) | G6: Avaliação de Impacto (X) | K6: Severidade (Y,X) | M6: Custo | N6: Prazo | AF6: Baixa - 2 | AG6: 2 | AI6: Muito Baixo - 2 | AJ6: 2
B7: CAUSA (Começa a frase com "Como Resultado ...") | C7: RISCO (Começar a frase com "Pode ocorrer ...") | D7: CONSEQÜÊNCIA (Começar a frase com "O que acarretaria ...") | G7: Aumento no Custo (X1) | H7: Desvio no Cronograma (X2) | I7: (X1*X2) | J7: Resultado do Impacto (X1+X2) | L7: Riscos Colaterais | AF7: Moderada - 3 | AG7: 3 | AI7: Baixo - 3 | AJ7: 3
A8: =IF(Identificar!A8<>"",Identificar!A8,"") -> R01 | B8: =IF(Identificar!D8<>"",Identificar!D8,"") -> Como resultado de falha na API externa | C8: =IF(Identificar!E8<>"",Identificar!E8,"") -> Pode ocorrer queda na comunicação do sistema | D8: =IF(Identificar!F8<>"",Identificar!F8,"") -> Algumas funções podem parar de funcionar | E8: =IF(Identificar!G8<>"",Identificar!G8,"") -> Desenvolvedor Backend | F8: Alta - 0,4 | G8: Entre 10% e 20% - 1,40 | H8: Entre 5% e 10% - 2,20 | I8: =IF(G8<>"",IF(H8<>"",RIGHT(G8,4)*RIGHT(H8,4),""),"") -> 3.08 | J8: =IF(I8<>"",VLOOKUP(I8,'Sensibilidade ao Risco'!$E$2:$F$30,2,FALSE),"") -> Alta - 0,40 | K8: =IF(F8<>"",IF(J8<>"",(RIGHT(J8,3))*(RIGHT(F8,3)),""),"") -> 0.16 | L8: Atraso no projeto e aumento nos custos | M8: =ROUNDUP(Quantificar!G8/Qualificar!$M$2,2) -> 1 | N8: =ROUNDUP([5]Quantificar!H8/Qualificar!$M$3,2) -> #VALUE! | AF8: Alta - 4 | AG8: 4 | AI8: Baixo - 4 | AJ8: 4
A9: =IF(Identificar!A9<>"",Identificar!A9,"") -> R02 | B9: =IF([5]Identificar!D9<>"",[5]Identificar!D9,"") -> Como resultado de queda no servidor | C9: =IF([5]Identificar!E9<>"",[5]Identificar!E9,"") -> Pode ocorrer sistema fora do ar | D9: =IF([5]Identificar!F9<>"",[5]Identificar!F9,"") -> Usuários não conseguirão acessar a plataforma | E9: =IF([5]Identificar!G9<>"",[5]Identificar!G9,"") -> DevOps / Infraestrutura | F9: Alta - 0,4 | G9: Entre 10% e 20% - 1,40 | H9: Entre 10% e 20% - 2,40 | I9: =IF(G9<>"",IF(H9<>"",RIGHT(G9,4)*RIGHT(H9,4),""),"") -> 3.36 | J9: Muito Alta - 0,80 | K9: =IF(F9<>"",IF(J9<>"",(RIGHT(J9,3))*(RIGHT(F9,3)),""),"") -> 0.32 | M9: =ROUNDUP([5]Quantificar!G9/Qualificar!$M$2,2) -> 1.2 | N9: =ROUNDUP([5]Quantificar!H9/Qualificar!$M$3,2) -> #VALUE!
A10: =IF(Identificar!A10<>"",Identificar!A10,"") -> R03 | B10: =IF([5]Identificar!D10<>"",[5]Identificar!D10,"") -> Como resultado de erro no desenvolvimento | C10: =IF([5]Identificar!E10<>"",[5]Identificar!E10,"") -> Pode ocorrer falha nas funcionalidades | D10: =IF([5]Identificar!F10<>"",[5]Identificar!F10,"") -> Usuário pode ter dificuldade para usar o sistema | E10: =IF([5]Identificar!G10<>"",[5]Identificar!G10,"") -> Desenvolvedor Web | F10: Moderada - 0,2 | G10: Até 10% - 1,20 | H10: Menor que 5% - 2,10 | I10: =IF(G10<>"",IF(H10<>"",RIGHT(G10,4)*RIGHT(H10,4),""),"") -> 2.52 | J10: Moderada - 0,20 | K10: =IF(F10<>"",IF(J10<>"",(RIGHT(J10,3))*(RIGHT(F10,3)),""),"") -> 0.04 | M10: =ROUNDUP([5]Quantificar!G10/Qualificar!$M$2,2) -> 0.8 | N10: =ROUNDUP([5]Quantificar!H10/Qualificar!$M$3,2) -> #VALUE!
A11: =IF(Identificar!A11<>"",Identificar!A11,"") -> R04 | B11: =IF([5]Identificar!D11<>"",[5]Identificar!D11,"") -> Como resultado de backup não realizado corretamente | C11: =IF([5]Identificar!E11<>"",[5]Identificar!E11,"") -> Pode ocorrer perda de dados importantes | D11: =IF([5]Identificar!F11<>"",[5]Identificar!F11,"") -> O projeto pode precisar refazer informações | E11: =IF([5]Identificar!G11<>"",[5]Identificar!G11,"") -> DevOps / Infraestrutura | F11: Baixa - 0,1 | G11: Até 10% - 1,20 | H11: Insignificante - 2,05 | I11: =IF(G11<>"",IF(H11<>"",RIGHT(G11,4)*RIGHT(H11,4),""),"") -> 2.46 | J11: Moderada - 0,20 | K11: =IF(F11<>"",IF(J11<>"",(RIGHT(J11,3))*(RIGHT(F11,3)),""),"") -> 0.02 | M11: =ROUNDUP([5]Quantificar!G11/Qualificar!$M$2,2) -> 1.5 | N11: =ROUNDUP([5]Quantificar!H11/Qualificar!$M$3,2) -> #VALUE!
A12: =IF(Identificar!A12<>"",Identificar!A12,"") -> R05 | B12: =IF([5]Identificar!D12<>"",[5]Identificar!D12,"") -> Como resultado de exclusão ou corrupção de arquivos | C12: =IF([5]Identificar!E12<>"",[5]Identificar!E12,"") -> Pode ocorrer perda de documentos do projeto | D12: =IF([5]Identificar!F12<>"",[5]Identificar!F12,"") -> A equipe pode ter retrabalho | E12: =IF([5]Identificar!G12<>"",[5]Identificar!G12,"") -> Gerente do Projeto | F12: Baixa - 0,1 | G12: Até 10% - 1,20 | H12: Menor que 5% - 2,10 | I12: =IF(G12<>"",IF(H12<>"",RIGHT(G12,4)*RIGHT(H12,4),""),"") -> 2.52 | J12: Moderada - 0,20 | K12: =IF(F12<>"",IF(J12<>"",(RIGHT(J12,3))*(RIGHT(F12,3)),""),"") -> 0.02 | M12: =ROUNDUP([5]Quantificar!G12/Qualificar!$M$2,2) -> 1 | N12: =ROUNDUP([5]Quantificar!H12/Qualificar!$M$3,2) -> #VALUE!
A13: =IF(Identificar!A13<>"",Identificar!A13,"") -> R06 | B13: =IF([5]Identificar!D13<>"",[5]Identificar!D13,"") -> Como resultado de falha na conexão com o banco | C13: =IF([5]Identificar!E13<>"",[5]Identificar!E13,"") -> Pode ocorrer lentidão ou erro nas consultas | D13: =IF([5]Identificar!F13<>"",[5]Identificar!F13,"") -> Os dashboards podem não carregar corretamente | E13: =IF([5]Identificar!G13<>"",[5]Identificar!G13,"") -> DBA / Banco de Dados | F13: Moderada - 0,2 | G13: Entre 10% e 20% - 1,40 | H13: Entre 5% e 10% - 2,20 | I13: =IF(G13<>"",IF(H13<>"",RIGHT(G13,4)*RIGHT(H13,4),""),"") -> 3.08 | J13: Alta - 0,40 | K13: =IF(F13<>"",IF(J13<>"",(RIGHT(J13,3))*(RIGHT(F13,3)),""),"") -> 0.08 | M13: =ROUNDUP([5]Quantificar!G13/Qualificar!$M$2,2) -> 2 | N13: =ROUNDUP([5]Quantificar!H13/Qualificar!$M$3,2) -> #VALUE!
A14: =IF(Identificar!A14<>"",Identificar!A14,"") -> R07 | B14: =IF([5]Identificar!D14<>"",[5]Identificar!D14,"") -> Como resultado do uso de hospedagem de baixo custo | C14: =IF([5]Identificar!E14<>"",[5]Identificar!E14,"") -> Pode ocorrer falta de recursos no servidor | D14: =IF([5]Identificar!F14<>"",[5]Identificar!F14,"") -> O sistema pode ficar lento | E14: =IF([5]Identificar!G14<>"",[5]Identificar!G14,"") -> DevOps / Infraestrutura | F14: Alta - 0,4 | G14: Entre 10% e 20% - 1,40 | H14: Entre 10% e 20% - 2,40 | I14: =IF(G14<>"",IF(H14<>"",RIGHT(G14,4)*RIGHT(H14,4),""),"") -> 3.36 | J14: Muito Alta - 0,80 | K14: =IF(F14<>"",IF(J14<>"",(RIGHT(J14,3))*(RIGHT(F14,3)),""),"") -> 0.32 | M14: =ROUNDUP([5]Quantificar!G14/Qualificar!$M$2,2) -> 0.5 | N14: =ROUNDUP([5]Quantificar!H14/Qualificar!$M$3,2) -> #VALUE!
A15: =IF(Identificar!A15<>"",Identificar!A15,"") -> R08 | B15: =IF([5]Identificar!D15<>"",[5]Identificar!D15,"") -> Como resultado de senha fraca ou falha de autenticação | C15: =IF([5]Identificar!E15<>"",[5]Identificar!E15,"") -> Pode ocorrer acesso não autorizado | D15: =IF([5]Identificar!F15<>"",[5]Identificar!F15,"") -> Informações podem ser expostas | E15: =IF([5]Identificar!G15<>"",[5]Identificar!G15,"") -> Analista de Segurança | F15: Baixa - 0,1 | G15: Até 10% - 1,20 | H15: Menor que 5% - 2,10 | I15: =IF(G15<>"",IF(H15<>"",RIGHT(G15,4)*RIGHT(H15,4),""),"") -> 2.52 | J15: Moderada - 0,20 | K15: =IF(F15<>"",IF(J15<>"",(RIGHT(J15,3))*(RIGHT(F15,3)),""),"") -> 0.02 | M15: =ROUNDUP([5]Quantificar!G15/Qualificar!$M$2,2) -> 2.5 | N15: =ROUNDUP([5]Quantificar!H15/Qualificar!$M$3,2) -> #VALUE!
A16: =IF(Identificar!A16<>"",Identificar!A16,"") -> R09 | B16: =IF([5]Identificar!D16<>"",[5]Identificar!D16,"") -> Como resultado de bases desatualizadas ou incompletas | C16: =IF([5]Identificar!E16<>"",[5]Identificar!E16,"") -> Pode ocorrer análise errada dos bairros e cidades | D16: =IF([5]Identificar!F16<>"",[5]Identificar!F16,"") -> Os resultados podem perder confiança | E16: =IF([5]Identificar!G16<>"",[5]Identificar!G16,"") -> Analista de Dados | F16: Moderada - 0,2 | G16: Entre 10% e 20% - 1,40 | H16: Entre 5% e 10% - 2,20 | I16: =IF(G16<>"",IF(H16<>"",RIGHT(G16,4)*RIGHT(H16,4),""),"") -> 3.08 | J16: Alta - 0,40 | K16: =IF(F16<>"",IF(J16<>"",(RIGHT(J16,3))*(RIGHT(F16,3)),""),"") -> 0.08 | M16: =ROUNDUP([5]Quantificar!G16/Qualificar!$M$2,2) -> 1.8 | N16: =ROUNDUP([5]Quantificar!H16/Qualificar!$M$3,2) -> #VALUE!
A17: =IF(Identificar!A17<>"",Identificar!A17,"") -> R10 | B17: =IF([5]Identificar!D17<>"",[5]Identificar!D17,"") -> Como resultado de erro na integração com fontes externas | C17: =IF([5]Identificar!E17<>"",[5]Identificar!E17,"") -> Pode ocorrer falha na coleta automática | D17: =IF([5]Identificar!F17<>"",[5]Identificar!F17,"") -> O sistema pode ficar sem dados atualizados | E17: =IF([5]Identificar!G17<>"",[5]Identificar!G17,"") -> Desenvolvedor Backend | F17: Alta - 0,4 | G17: Entre 10% e 20% - 1,40 | H17: Entre 10% e 20% - 2,40 | I17: =IF(G17<>"",IF(H17<>"",RIGHT(G17,4)*RIGHT(H17,4),""),"") -> 3.36 | J17: Muito Alta - 0,80 | K17: =IF(F17<>"",IF(J17<>"",(RIGHT(J17,3))*(RIGHT(F17,3)),""),"") -> 0.32 | M17: =ROUNDUP([5]Quantificar!G17/Qualificar!$M$2,2) -> 1.2 | N17: =ROUNDUP([5]Quantificar!H17/Qualificar!$M$3,2) -> #VALUE!
A18: =IF(Identificar!A18<>"",Identificar!A18,"") -> R11 | B18: =IF([5]Identificar!D18<>"",[5]Identificar!D18,"") -> Como resultado de telas mal ajustadas | C18: =IF([5]Identificar!E18<>"",[5]Identificar!E18,"") -> Pode ocorrer dificuldade de navegação | D18: =IF([5]Identificar!F18<>"",[5]Identificar!F18,"") -> O usuário pode abandonar a plataforma | E18: =IF([5]Identificar!G18<>"",[5]Identificar!G18,"") -> Designer UX/UI | F18: Baixa - 0,1 | G18: Até 10% - 1,20 | H18: Menor que 5% - 2,10 | I18: =IF(G18<>"",IF(H18<>"",RIGHT(G18,4)*RIGHT(H18,4),""),"") -> 2.52 | J18: Moderada - 0,20 | K18: =IF(F18<>"",IF(J18<>"",(RIGHT(J18,3))*(RIGHT(F18,3)),""),"") -> 0.02 | M18: =ROUNDUP([5]Quantificar!G18/Qualificar!$M$2,2) -> 0.4 | N18: =ROUNDUP([5]Quantificar!H18/Qualificar!$M$3,2) -> #VALUE!
A19: =IF(Identificar!A19<>"",Identificar!A19,"") -> R12 | B19: =IF([5]Identificar!D19<>"",[5]Identificar!D19,"") -> Como resultado de erro na função de exportar dados | C19: =IF([5]Identificar!E19<>"",[5]Identificar!E19,"") -> Pode ocorrer falha ao gerar relatórios | D19: =IF([5]Identificar!F19<>"",[5]Identificar!F19,"") -> O usuário não conseguirá salvar as análises | E19: =IF([5]Identificar!G19<>"",[5]Identificar!G19,"") -> Desenvolvedor Web | F19: Moderada - 0,2 | G19: Até 10% - 1,20 | H19: Entre 5% e 10% - 2,20 | I19: =IF(G19<>"",IF(H19<>"",RIGHT(G19,4)*RIGHT(H19,4),""),"") -> 2.64 | J19: Alta - 0,40 | K19: =IF(F19<>"",IF(J19<>"",(RIGHT(J19,3))*(RIGHT(F19,3)),""),"") -> 0.08 | M19: =ROUNDUP([5]Quantificar!G19/Qualificar!$M$2,2) -> 0.6 | N19: =ROUNDUP([5]Quantificar!H19/Qualificar!$M$3,2) -> #VALUE!
A20: =IF(Identificar!A20<>"",Identificar!A20,"") -> R13 | B20: =IF([5]Identificar!D20<>"",[5]Identificar!D20,"") -> Como resultado de bug nas bibliotecas de gráficos | C20: =IF([5]Identificar!E20<>"",[5]Identificar!E20,"") -> Pode ocorrer gráfico incorreto ou não carregado | D20: =IF([5]Identificar!F20<>"",[5]Identificar!F20,"") -> A análise visual pode ficar prejudicada | E20: =IF([5]Identificar!G20<>"",[5]Identificar!G20,"") -> Desenvolvedor Frontend | F20: Moderada - 0,2 | G20: Até 10% - 1,20 | H20: Entre 5% e 10% - 2,20 | I20: =IF(G20<>"",IF(H20<>"",RIGHT(G20,4)*RIGHT(H20,4),""),"") -> 2.64 | J20: Alta - 0,40 | K20: =IF(F20<>"",IF(J20<>"",(RIGHT(J20,3))*(RIGHT(F20,3)),""),"") -> 0.08 | M20: =ROUNDUP([5]Quantificar!G20/Qualificar!$M$2,2) -> 0.7 | N20: =ROUNDUP([5]Quantificar!H20/Qualificar!$M$3,2) -> #VALUE!
... A23: =IF(Identificar!A23<>"",Identificar!A23,"") -> R16 | B23: =IF([5]Identificar!D23<>"",[5]Identificar!D23,"") -> Como resultado de documentação incompleta | C23: =IF([5]Identificar!E23<>"",[5]Identificar!E23,"") -> Pode ocorrer dificuldade para corrigir problemas futuros | D23: =IF([5]Identificar!F23<>"",[5]Identificar!F23,"") -> A manutenção do sistema ficará mais difícil | E23: =IF([5]Identificar!G23<>"",[5]Identificar!G23,"") -> Analista de Documentação | F23: Muito baixa - 0,05 | G23: Insignificante - 1,05 | H23: Insignificante - 2,05 | I23: =IF(G23<>"",IF(H23<>"",RIGHT(G23,4)*RIGHT(H23,4),""),"") -> 2.1525 | J23: Muito baixa - 0,05 | K23: =IF(F23<>"",IF(J23<>"",(RIGHT(J23,3))*(RIGHT(F23,3)),""),"") -> 0.0025 | M23: =ROUNDUP([5]Quantificar!G23/Qualificar!$M$2,2) -> 0.2 | N23: =ROUNDUP([5]Quantificar!H23/Qualificar!$M$3,2) -> #VALUE!
F43: Insignificante - 1,05 | G43: Insignificante - 2,05 | H43: Muito baixa - 0,05
F44: Menor que 5% - 1,10 | G44: Menor que 5% - 2,10 | H44: Baixa - 0,1
F45: Entre 5% e 10% - 1,20 | G45: Entre 5% e 10% - 2,20 | H45: Moderada - 0,2
F46: Entre 10% e 20% - 1,40 | G46: Entre 10% e 20% - 2,40 | H46: Alta - 0,4
F47: Maior que 20% - 1,80 | G47: Maior que 20% - 2,80 | H47: Muito Alta - 0,8

Sheet Quantificar
A1: Quantificação dos Riscos | AB1: Probabilidade | AE1: Impacto
A4: =[5]Identificar!A4 -> UrbanScore
AB5: Muito Baixa - 1 | AC5: 1 | AE5: Muito Baixo - 1 | AF5: 1
A6: ID | B6: Declaração do Risco | E6: Resp. | G6: Impacto no Custo (Considerar qtde. de horas como unidade de medida, inclusive, a maior ou menor) | H6: Impacto no Cronograma (Colocar qtde. de dias de redução ou atraso no cronograma) | I6: Observação | J6: Plano de Prevenção | K6: Plano de Contingência | AB6: Baixa - 2 | AC6: 2 | AE6: Muito Baixo - 2 | AF6: 2
B7: CAUSA (Começa a frase com "Como Resultado ...") | C7: RISCO (Começar a frase com "Pode ocorrer ...") | D7: CONSEQÜÊNCIA (Começar a frase com "O que acarretaria ...") | F7: Riscos Colaterais | AB7: Moderada - 3 | AC7: 3 | AE7: Baixo - 3 | AF7: 3
A8: =IF(Identificar!A8<>"",Identificar!A8,"") -> R01 | B8: =IF(Identificar!D8<>"",Identificar!D8,"") -> Como resultado de falha na API externa | C8: =IF(Identificar!E8<>"",Identificar!E8,"") -> Pode ocorrer queda na comunicação do sistema | D8: =IF(Identificar!F8<>"",Identificar!F8,"") -> Algumas funções podem parar de funcionar | E8: =IF(Identificar!G8<>"",Identificar!G8,"") -> Desenvolvedor Backend | F8: API cair | G8: 10000 | H8: 5 dias | I8: Pode atrasar funções que dependem da integração | J8: Monitorar a API e testar as integrações | K8: Usar API reserva ou corrigir a integração | AB8: Alta - 4 | AC8: 4 | AE8: Baixo - 4 | AF8: 4
A9: =IF(Identificar!A9<>"",Identificar!A9,"") -> R02 | B9: =IF(Identificar!D9<>"",Identificar!D9,"") -> Como resultado de queda no servidor | C9: =IF(Identificar!E9<>"",Identificar!E9,"") -> Pode ocorrer sistema fora do ar | D9: =IF(Identificar!F9<>"",Identificar!F9,"") -> Usuários não conseguirão acessar a plataforma | E9: =IF(Identificar!G9<>"",Identificar!G9,"") -> DevOps / Infraestrutura | F9: Servidor cair | G9: 12000 | H9: 7 dias | I9: Sistema pode ficar fora do ar | J9: Contratar servidor confiável e acompanhar disponibilidade | K9: Acionar suporte da hospedagem e subir sistema reserva
A10: =IF(Identificar!A10<>"",Identificar!A10,"") -> R03 | B10: =IF(Identificar!D10<>"",Identificar!D10,"") -> Como resultado de erro no desenvolvimento | C10: =IF(Identificar!E10<>"",Identificar!E10,"") -> Pode ocorrer falha nas funcionalidades | D10: =IF(Identificar!F10<>"",Identificar!F10,"") -> Usuário pode ter dificuldade para usar o sistema | E10: =IF(Identificar!G10<>"",Identificar!G10,"") -> Desenvolvedor Web | F10: Aplicação com bug | G10: 8000 | H10: 4 dias | I10: Correção rápida antes da entrega | J10: Fazer testes durante o desenvolvimento | K10: Corrigir bugs e publicar nova versão
A11: =IF(Identificar!A11<>"",Identificar!A11,"") -> R04 | B11: =IF(Identificar!D11<>"",Identificar!D11,"") -> Como resultado de backup não realizado corretamente | C11: =IF(Identificar!E11<>"",Identificar!E11,"") -> Pode ocorrer perda de dados importantes | D11: =IF(Identificar!F11<>"",Identificar!F11,"") -> O projeto pode precisar refazer informações | E11: =IF(Identificar!G11<>"",Identificar!G11,"") -> DevOps / Infraestrutura | F11: Falha em backup | G11: 15000 | H11: 10 dias | I11: Pode precisar restaurar ou refazer dados | J11: Programar backup automático todos os dias | K11: Restaurar o último backup salvo
A12: =IF(Identificar!A12<>"",Identificar!A12,"") -> R05 | B12: =IF(Identificar!D12<>"",Identificar!D12,"") -> Como resultado de exclusão ou corrupção de arquivos | C12: =IF(Identificar!E12<>"",Identificar!E12,"") -> Pode ocorrer perda de documentos do projeto | D12: =IF(Identificar!F12<>"",Identificar!F12,"") -> A equipe pode ter retrabalho | E12: =IF(Identificar!G12<>"",Identificar!G12,"") -> Gerente do Projeto | F12: Perda de arquivo | G12: 10000 | H12: 5 dias | I12: Retrabalho para recuperar documentos | J12: Organizar arquivos em nuvem com controle de acesso | K12: Recuperar cópias salvas ou refazer arquivos
A13: =IF(Identificar!A13<>"",Identificar!A13,"") -> R06 | B13: =IF(Identificar!D13<>"",Identificar!D13,"") -> Como resultado de falha na conexão com o banco | C13: =IF(Identificar!E13<>"",Identificar!E13,"") -> Pode ocorrer lentidão ou erro nas consultas | D13: =IF(Identificar!F13<>"",Identificar!F13,"") -> Os dashboards podem não carregar corretamente | E13: =IF(Identificar!G13<>"",Identificar!G13,"") -> DBA / Banco de Dados | F13: Erro no banco de dados | G13: 20000 | H13: 12 dias | I13: Pode afetar dashboards e consultas | J13: Testar conexão e desempenho do banco | K13: Corrigir conexão e reiniciar serviços
A14: =IF(Identificar!A14<>"",Identificar!A14,"") -> R07 | B14: =IF(Identificar!D14<>"",Identificar!D14,"") -> Como resultado do uso de hospedagem de baixo custo | C14: =IF(Identificar!E14<>"",Identificar!E14,"") -> Pode ocorrer falta de recursos no servidor | D14: =IF(Identificar!F14<>"",Identificar!F14,"") -> O sistema pode ficar lento | E14: =IF(Identificar!G14<>"",Identificar!G14,"") -> DevOps / Infraestrutura | F14: Limite da nuvem | G14: 5000 | H14: 3 dias | I14: Pode precisar aumentar o plano | J14: Acompanhar limite da hospedagem usada | K14: Aumentar o plano da nuvem se precisar
A15: =IF(Identificar!A15<>"",Identificar!A15,"") -> R08 | B15: =IF(Identificar!D15<>"",Identificar!D15,"") -> Como resultado de senha fraca ou falha de autenticação | C15: =IF(Identificar!E15<>"",Identificar!E15,"") -> Pode ocorrer acesso não autorizado | D15: =IF(Identificar!F15<>"",Identificar!F15,"") -> Informações podem ser expostas | E15: =IF(Identificar!G15<>"",Identificar!G15,"") -> Analista de Segurança | F15: Acesso indevido | G15: 25000 | H15: 15 dias | I15: Necessário corrigir segurança e senhas | J15: Usar senha forte, SSL e controle de acesso | K15: Bloquear acessos suspeitos e trocar senhas
A16: =IF(Identificar!A16<>"",Identificar!A16,"") -> R09 | B16: =IF(Identificar!D16<>"",Identificar!D16,"") -> Como resultado de bases desatualizadas ou incompletas | C16: =IF(Identificar!E16<>"",Identificar!E16,"") -> Pode ocorrer análise errada dos bairros e cidades | D16: =IF(Identificar!F16<>"",Identificar!F16,"") -> Os resultados podem perder confiança | E16: =IF(Identificar!G16<>"",Identificar!G16,"") -> Analista de Dados | F16: Dados incorretos | G16: 18000 | H16: 10 dias | I16: Pode gerar análises erradas | J16: Conferir a qualidade das bases antes de usar | K16: Atualizar ou trocar a base de dados
A17: =IF(Identificar!A17<>"",Identificar!A17,"") -> R10 | B17: =IF(Identificar!D17<>"",Identificar!D17,"") -> Como resultado de erro na integração com fontes externas | C17: =IF(Identificar!E17<>"",Identificar!E17,"") -> Pode ocorrer falha na coleta automática | D17: =IF(Identificar!F17<>"",Identificar!F17,"") -> O sistema pode ficar sem dados atualizados | E17: =IF(Identificar!G17<>"",Identificar!G17,"") -> Desenvolvedor Backend | F17: Falha na integração | G17: 12000 | H17: 6 dias | I17: Coleta automática pode parar | J17: Testar a coleta automática com frequência | K17: Fazer coleta manual até corrigir
A18: =IF(Identificar!A18<>"",Identificar!A18,"") -> R11 | B18: =IF(Identificar!D18<>"",Identificar!D18,"") -> Como resultado de telas mal ajustadas | C18: =IF(Identificar!E18<>"",Identificar!E18,"") -> Pode ocorrer dificuldade de navegação | D18: =IF(Identificar!F18<>"",Identificar!F18,"") -> O usuário pode abandonar a plataforma | E18: =IF(Identificar!G18<>"",Identificar!G18,"") -> Designer UX/UI | F18: Erro visual na interface | G18: 4000 | H18: 2 dias | I18: Ajuste simples de tela | J18: Testar as telas com usuários | K18: Ajustar rapidamente as telas com problema
A19: =IF(Identificar!A19<>"",Identificar!A19,"") -> R12 | B19: =IF(Identificar!D19<>"",Identificar!D19,"") -> Como resultado de erro na função de exportar dados | C19: =IF(Identificar!E19<>"",Identificar!E19,"") -> Pode ocorrer falha ao gerar relatórios | D19: =IF(Identificar!F19<>"",Identificar!F19,"") -> O usuário não conseguirá salvar as análises | E19: =IF(Identificar!G19<>"",Identificar!G19,"") -> Desenvolvedor Web | F19: Falha na exportação | G19: 6000 | H19: 3 dias | I19: Usuário pode não conseguir baixar relatórios | J19: Testar a exportação antes da entrega | K19: Gerar relatório manual ou corrigir função
A20: =IF(Identificar!A20<>"",Identificar!A20,"") -> R13 | B20: =IF(Identificar!D20<>"",Identificar!D20,"") -> Como resultado de bug nas bibliotecas de gráficos | C20: =IF(Identificar!E20<>"",Identificar!E20,"") -> Pode ocorrer gráfico incorreto ou não carregado | D20: =IF(Identificar!F20<>"",Identificar!F20,"") -> A análise visual pode ficar prejudicada | E20: =IF(Identificar!G20<>"",Identificar!G20,"") -> Desenvolvedor Frontend | F20: Gráficos com erro | G20: 7000 | H20: 4 dias | I20: Pode prejudicar a leitura dos dados | J20: Testar gráficos em diferentes telas | K20: Corrigir biblioteca ou trocar o modelo do gráfico
... A23: =IF(Identificar!A23<>"",Identificar!A23,"") -> R16 | B23: =IF(Identificar!D23<>"",Identificar!D23,"") -> Como resultado de documentação incompleta | C23: =IF(Identificar!E23<>"",Identificar!E23,"") -> Pode ocorrer dificuldade para corrigir problemas futuros | D23: =IF(Identificar!F23<>"",Identificar!F23,"") -> A manutenção do sistema ficará mais difícil | E23: =IF(Identificar!G23<>"",Identificar!G23,"") -> Analista de Documentação | F23: Documentação incompleta | G23: 2000 | H23: 1 dia | I23: Impacto baixo, pode ser ajustado depois | J23: Registrar as informações principais do sistema | K23: Completar a documentação depois da entrega

Sheet Histórico de evolução(não)
A1: Não precisa preencher, pois o projeto não será acompanhado.
A2: Versão | B2: Autor | C2: Id Risco | D2: Categoria | E2: Data | F2: Situação anterior | G2: Situação Atual | H2: Motivo
A3: 1 | C3: R01 | E3: 39511 | F3: 0 | G3: 0.32 | H3: Levantamento inicial
A4: 1 | C4: R02 | E4: 39511 | F4: 0 | G4: 0.005 | H4: Levantamento inicial
A5: 1 | C5: R03 | E5: 39511 | F5: 0 | G5: 0.01 | H5: Levantamento inicial
A6: 1 | C6: R04 | E6: 39511 | F6: 0 | G6: 0.02 | H6: Levantamento inicial
A7: 1 | C7: R05 | E7: 39511 | F7: 0 | G7: 0.02 | H7: Levantamento inicial
A8: 1 | C8: R06 | E8: 39511 | F8: 0 | G8: 0.02 | H8: Levantamento inicial
A9: 1 | C9: R07 | E9: 39511 | F9: 0 | G9: 0.04 | H9: Levantamento inicial
A10: 1 | C10: R08 | E10: 39511 | F10: 0 | G10: 0.01 | H10: Levantamento inicial
A11: 1 | C11: R09 | E11: 39511 | F11: 0 | G11: 0.04 | H11: Levantamento inicial
A12: 1 | C12: R10 | E12: 39511 | F12: 0 | G12: 0.005 | H12: Levantamento inicial
A13: 1 | C13: R11 | E13: 39511 | F13: 0 | G13: 0.01 | H13: Levantamento inicial
A14: 1 | C14: R12 | E14: 39511 | F14: 0 | G14: 0.02 | H14: Levantamento inicial
A15: 1 | C15: R13 | E15: 39511 | F15: 0 | G15: 0.04 | H15: Levantamento inicial

Sheet Sensibilidade ao Risco
A1: Custo | B1: Peso1 | C1: Cronograma | D1: Peso2 | E1: Peso1 X Peso2 | F1: Impacto
A2: Aumento de custo Insignificante | B2: 1.05 | C2: Desvio no cronograma insignificante | D2: 2.05 | E2: =B2*D2 -> 2.1525 | F2: Muito baixa - 0,05
A3: Aumento de custo Insignificante | B3: 1.05 | C3: Desvio menor que 5% no cronograma | D3: 2.1 | E3: =B3*D3 -> 2.205 | F3: Baixa - 0,10
A4: Aumento de custo Insignificante | B4: 1.05 | C4: Desvio total entre 5% e 10% no cronograma | D4: 2.2 | E4: =B4*D4 -> 2.31 | F4: Baixa - 0,10
A5: Aumento de custo Insignificante | B5: 1.05 | C5: Desvio total entre 10% e 20% no cronograma | D5: 2.4 | E5: =B5*D5 -> 2.52 | F5: Moderada - 0,20
A6: Aumento de custo Insignificante | B6: 1.05 | C6: Desvio total maior que 20% no cronograma | D6: 2.8 | E6: =B6*D6 -> 2.94 | F6: Alta - 0,40
A8: Menos de 5% de aumento no custo | B8: 1.1 | C8: Desvio no cronograma insignificante | D8: 2.05 | E8: =B8*D8 -> 2.255 | F8: Baixa - 0,10
A9: Menos de 5% de aumento no custo | B9: 1.1 | C9: Desvio menor que 5% no cronograma | D9: 2.1 | E9: =B9*D9 -> 2.31 | F9: Baixa - 0,10
A10: Menos de 5% de aumento no custo | B10: 1.1 | C10: Desvio total entre 5% e 10% no cronograma | D10: 2.2 | E10: =B10*D10 -> 2.42 | F10: Moderada - 0,20
A11: Menos de 5% de aumento no custo | B11: 1.1 | C11: Desvio total entre 10% e 20% no cronograma | D11: 2.4 | E11: =B11*D11 -> 2.64 | F11: Alta - 0,40
A12: Menos de 5% de aumento no custo | B12: 1.1 | C12: Desvio total maior que 20% no cronograma | D12: 2.8 | E12: =B12*D12 -> 3.08 | F12: Alta - 0,40
A14: entre 5% e 10% de aumento do custo | B14: 1.2 | C14: Desvio no cronograma insignificante | D14: 2.05 | E14: =B14*D14 -> 2.46 | F14: Moderada - 0,20
A15: entre 5% e 10% de aumento do custo | B15: 1.2 | C15: Desvio menor que 5% no cronograma | D15: 2.1 | E15: =B15*D15 -> 2.52 | F15: Moderada - 0,20
... A30: Mais de 20% de aumento nos custos | B30: 1.8 | C30: Desvio total maior que 20% no cronograma | D30: 2.8 | E30: =B30*D30 -> 5.04 | F30: Muito Alta - 0,80
A31: Muito baixa - 0,05
A32: Baixa - 0,10
A33: Moderada - 0,20
A34: Alta - 0,40
A35: Muito Alta - 0,80

Sheet Gráfico de Gantt
E3: Saúde e bem-estar na palma da sua mão
A5: Insira o nome do Líder do projeto na célula B3. Insira a data de Início do projeto na célula E3. Início do projeto: o rótulo está na célula C3. | D5: Líder do projeto: Gerente de Projeto | E5: Início do projeto: | G5: 45160
A6: A semana de exibição na célula E4 representa a semana inicial a ser exibida no cronograma do projeto na célula I4. A data de início do projeto é considerada Semana 1. Para alterar a semana de exibição, basta inserir um novo número da semana na célula E4. A data inicial para cada semana, começando com a semana de exibição na célula E4, começa na célula I4 e é calculada automaticamente. Há 8 semanas representadas nesse modo de exibição que vão da célula I4 a célula BF4. Você não deve modificar essas células. Semana de exibição: o rótulo está na célula C4. | E6: Semana de exibição: | G6: 1 | K6: =K7 -> 45159 | R6: =R7 -> 45166 | Y6: =Y7 -> 45173 | AF6: =AF7 -> 45180 | AM6: =AM7 -> 45187 | AT6: =AT7 -> 45194 | BA6: =BA7 -> 45201 | BH6: =BH7 -> 45208
A7: As células I5 a BL5 contêm o número de dias da semana representado no bloco de células acima de cada célula de data e são calculadas automaticamente. Você não deve modificar essas células. A data de hoje é contornada em vermelho (hex #AD3815) a partir da data de hoje na linha 5, passando pela coluna de data inteira até o final do cronograma do projeto. | K7: =Início_do_projeto-WEEKDAY(Início_do_projeto,1)+2+7*(Semana_de_exibição-1) -> 45159 | L7: =K7+1 -> 45160 | M7: =L7+1 -> 45161 | N7: =M7+1 -> 45162 | O7: =N7+1 -> 45163 | P7: =O7+1 -> 45164 | Q7: =P7+1 -> 45165 | R7: =Q7+1 -> 45166 | S7: =R7+1 -> 45167 | ... BN7: =BM7+1 -> 45214
A8: Esta linha inclui cabeçalhos do cronograma do projeto que estão abaixo deles. Navegue de B6 a BL6 para ouvir o conteúdo. A primeira letra de cada dia da semana da data acima daquele cabeçalho começa na célula I6 e continua até a célula BL6. Todo o gráfico de linha do tempo de projeto é gerado automaticamente com base nas datas de início e término inseridas, usando os formatos condicionais. Não modifique o conteúdo nas células dentro das colunas após a coluna I, começando na célula I7. | D8: TAREFA | E8: ATRIBUÍDO PARA | F8: PROGRESSO | G8: INÍCIO | H8: TÉRMINO | J8: DIAS | K8: =LEFT(TEXT(K7,"ddd"),1) -> s | L8: =LEFT(TEXT(L7,"ddd"),1) -> t | M8: =LEFT(TEXT(M7,"ddd"),1) -> q | N8: =LEFT(TEXT(N7,"ddd"),1) -> q | O8: =LEFT(TEXT(O7,"ddd"),1) -> s | P8: =LEFT(TEXT(P7,"ddd"),1) -> s | Q8: =LEFT(TEXT(Q7,"ddd"),1) -> d | R8: =LEFT(TEXT(R7,"ddd"),1) -> s | ... BN8: =LEFT(TEXT(BN7,"ddd"),1) -> d
A9: Não exclua esta linha. Esta linha ficará oculta para preservar uma fórmula usada para realçar o dia atual no cronograma do projeto. | J9: =IF(OR(ISBLANK(início_da_tarefa),ISBLANK(término_da_tarefa)),"",término_da_tarefa-início_da_tarefa+1) -> #NAME?
A10: A célula B8 contém o título do exemplo da Fase 1. Insira um novo Título na célula B8. Na célula C8, insira o nome a atribuir à fase, caso ela se aplique ao seu projeto. Na célula D8, insira o Progresso para a fase inteira, caso ela se aplique ao seu projeto. Nas células E8 e F8, insira as datas de início e término para a fase inteira, caso ela se aplique ao seu projeto. O gráfico de Gantt preenche automaticamente as datas apropriadas e sombreia de acordo com o andamento inserido. Para excluir a fase e trabalhar apenas nas tarefas, basta excluir essa linha. | D10: Iniciação | J10: =IF(OR(ISBLANK(início_da_tarefa),ISBLANK(término_da_tarefa)),"",término_da_tarefa-início_da_tarefa+1) -> #NAME?
A11: A célula B9 contém a tarefa de exemplo "Tarefa 1". Insira um novo nome da tarefa na célula B9. Insira uma pessoa para atribuir a tarefa na célula C9. Insira o andamento da tarefa na célula D9. Uma barra de progresso é exibida na célula e fica sombreada de acordo com o número na célula. Por exemplo, 50% de progresso sombreia metade da célula. Insira a data de início da tarefa na célula E9. Insira a data de término da tarefa na célula F9. Uma barra de status sombreada das datas inseridas aparece em blocos começando na célula I9 até BL9. | D11: Definir os objetivos do aplicativo e sua proposta de valor | G11: =Início_do_projeto -> 45160 | H11: =G11+3 -> 45163 | J11: =IF(OR(ISBLANK(início_da_tarefa),ISBLANK(término_da_tarefa)),"",término_da_tarefa-início_da_tarefa+1) -> #NAME?
A12: As linhas 10 a 13 repetem o padrão da linha 9. Repita as instruções da célula A9 para todas as linhas de tarefas nesta planilha. Substitua os dados de exemplo. Um exemplo de outra fase começa na célula A14. Continue inserindo tarefas nas células A10 a A13 ou vá para a célula A14 para saber mais. | D12: Tarefa 2 | J12: =IF(OR(ISBLANK(início_da_tarefa),ISBLANK(término_da_tarefa)),"",término_da_tarefa-início_da_tarefa+1) -> #NAME?
D13: Tarefa 3 | J13: =IF(OR(ISBLANK(início_da_tarefa),ISBLANK(término_da_tarefa)),"",término_da_tarefa-início_da_tarefa+1) -> #NAME?
D14: Tarefa 4 | J14: =IF(OR(ISBLANK(início_da_tarefa),ISBLANK(término_da_tarefa)),"",término_da_tarefa-início_da_tarefa+1) -> #NAME?
D15: Tarefa 5 | J15: =IF(OR(ISBLANK(início_da_tarefa),ISBLANK(término_da_tarefa)),"",término_da_tarefa-início_da_tarefa+1) -> #NAME?
A16: A célula à direita contém o título do exemplo da Fase 2. Você pode criar uma nova fase a qualquer momento na coluna B. Este cronograma de projeto não exige fases. Para remover a fase, basta excluir a linha. Para criar um novo bloco de fases nesta linha, digite um novo Título na célula à direita. Para continuar a adicionar tarefas à fase acima, insira uma nova linha acima desta e preencha os dados da tarefa como na instrução da célula A9. Atualize os detalhes da Fase na célula à direita, com base nas instruções da célula A8. Continue navegando para baixo nas células da coluna A para saber mais. Se você ainda não adicionou as novas linhas nesta planilha, encontrará 2 exemplos adicionais de blocos de fase que foram criados nas células B20 e B26. Caso contrário, navegue pelas células da coluna A para localizar os blocos adicionais. Repita as instruções das células A8 e A9 sempre que precisar. | D16: Título Fase 2 | J16: =IF(OR(ISBLANK(início_da_tarefa),ISBLANK(término_da_tarefa)),"",término_da_tarefa-início_da_tarefa+1) -> #NAME?
D17: Tarefa 1 | J17: =IF(OR(ISBLANK(início_da_tarefa),ISBLANK(término_da_tarefa)),"",término_da_tarefa-início_da_tarefa+1) -> #NAME?
D18: Tarefa 2 | J18: =IF(OR(ISBLANK(início_da_tarefa),ISBLANK(término_da_tarefa)),"",término_da_tarefa-início_da_tarefa+1) -> #NAME?
D19: Tarefa 3 | J19: =IF(OR(ISBLANK(início_da_tarefa),ISBLANK(término_da_tarefa)),"",término_da_tarefa-início_da_tarefa+1) -> #NAME?
D20: Tarefa 4 | J20: =IF(OR(ISBLANK(início_da_tarefa),ISBLANK(término_da_tarefa)),"",término_da_tarefa-início_da_tarefa+1) -> #NAME?
D21: Tarefa 5 | J21: =IF(OR(ISBLANK(início_da_tarefa),ISBLANK(término_da_tarefa)),"",término_da_tarefa-início_da_tarefa+1) -> #NAME?
A22: Bloco de título de fase de exemplo | D22: Título Fase 3 | J22: =IF(OR(ISBLANK(início_da_tarefa),ISBLANK(término_da_tarefa)),"",término_da_tarefa-início_da_tarefa+1) -> #NAME?
D23: Tarefa 1 | J23: =IF(OR(ISBLANK(início_da_tarefa),ISBLANK(término_da_tarefa)),"",término_da_tarefa-início_da_tarefa+1) -> #NAME?
D24: Tarefa 2 | J24: =IF(OR(ISBLANK(início_da_tarefa),ISBLANK(término_da_tarefa)),"",término_da_tarefa-início_da_tarefa+1) -> #NAME?
D25: Tarefa 3 | J25: =IF(OR(ISBLANK(início_da_tarefa),ISBLANK(término_da_tarefa)),"",término_da_tarefa-início_da_tarefa+1) -> #NAME?
D26: Tarefa 4 | J26: =IF(OR(ISBLANK(início_da_tarefa),ISBLANK(término_da_tarefa)),"",término_da_tarefa-início_da_tarefa+1) -> #NAME?
D27: Tarefa 5 | J27: =IF(OR(ISBLANK(início_da_tarefa),ISBLANK(término_da_tarefa)),"",término_da_tarefa-início_da_tarefa+1) -> #NAME?
A28: Bloco de título de fase de exemplo | D28: Título Fase 4 | J28: =IF(OR(ISBLANK(início_da_tarefa),ISBLANK(término_da_tarefa)),"",término_da_tarefa-início_da_tarefa+1) -> #NAME?
D29: Tarefa 1 | G29: data | H29: data | J29: =IF(OR(ISBLANK(início_da_tarefa),ISBLANK(término_da_tarefa)),"",término_da_tarefa-início_da_tarefa+1) -> #NAME?
D30: Tarefa 2 | G30: data | H30: data | J30: =IF(OR(ISBLANK(início_da_tarefa),ISBLANK(término_da_tarefa)),"",término_da_tarefa-início_da_tarefa+1) -> #NAME?
D31: Tarefa 3 | G31: data | H31: data | J31: =IF(OR(ISBLANK(início_da_tarefa),ISBLANK(término_da_tarefa)),"",término_da_tarefa-início_da_tarefa+1) -> #NAME?
D32: Tarefa 4 | G32: data | H32: data | J32: =IF(OR(ISBLANK(início_da_tarefa),ISBLANK(término_da_tarefa)),"",término_da_tarefa-início_da_tarefa+1) -> #NAME?
D33: Tarefa 5 | G33: data | H33: data | J33: =IF(OR(ISBLANK(início_da_tarefa),ISBLANK(término_da_tarefa)),"",término_da_tarefa-início_da_tarefa+1) -> #NAME?
A34: Esta é uma linha vazia | J34: =IF(OR(ISBLANK(início_da_tarefa),ISBLANK(término_da_tarefa)),"",término_da_tarefa-início_da_tarefa+1) -> #NAME?
A35: Esta linha marca o final do Cronograma do projeto. NÃO insira nada nessa linha. Insira novas linhas ACIMA desta linha para continuar a construção do cronograma de projeto. | D35: Insira novas linhas ACIMA desta | J35: =IF(OR(ISBLANK(início_da_tarefa),ISBLANK(término_da_tarefa)),"",término_da_tarefa-início_da_tarefa+1) -> #NAME?

Sheet PV_dependência
A3: Dependência | B3: Responsável | C3: Etapas – Atividades - | D3: Ref | E3: Soma de Custos
A4: - | B4: - | C4: Ajustes de UX Baseados em Feedback | D4: 6.2 | E4: 6000
C5: Configuração de Assinaturas e Acessos | D5: 6.4 | E5: 9500
C6: Cronograma Detalhado | D6: 1.4 | E6: 2500
C7: Definição de requisitos detalhado | D7: 2.2 | E7: 2500
C8: Desenvolvimento frontend | D8: 4.2 | E8: 1500
C9: Encerramento do Ciclo de Desenvolvimento | D9: 6.6 | E9: 0
C10: Entrega Final | D10: 5.4 | E10: 500
C11: Estruturação do backend | D11: 4.1 | E11: 1500
C12: Fluxos de navegação | D12: 3.1 | E12: 10000
C13: Homologação dos Módulos analíticos | D13: 6.1 | E13: 6900
C14: Implantação (Go-Live) | D14: 5.3 | E14: 1500
C15: Iniciação | D15: 1.1 | E15: 8000
C16: Módulos Analíticos | D16: 4.3 | E16: 10500
... C26: Treinamento e Documentação Técnica | D26: 6.3 | E26: 5000
A27: 1.1 | B27: Henrique Jorge Martins Figueiredo | C27: Alinhamento Estratégico | D27: 1.1.2 | E27: 2000
C28: Definição do objetivo | D28: 1.1.1 | E28: 2000
A29: 1.1.1 | B29: Luiz Eduardo Souza Rocha | C29: Identificação de stakeholders | D29: 1.2.1 | E29: 800
A30: 1.1.1, 1.1.2 | B30: Pedro Augusto da Silva Macedo | C30: Formalização do project charter | D30: 1.1.3 | E30: 4000
A31: 1.1.2 | B31: Luiz Eduardo Souza Rocha | C31: Plano de comunicação com patrocinadores | D31: 1.2.2 | E31: 2000
A32: 1.1.3 | B32: Pedro Augusto da Silva Macedo | C32: Alocação do investimento | D32: 1.3.1 | E32: 2500
A33: 1.3 | B33: Luiz Eduardo Souza Rocha | C33: Gestão de stakeholders | D33: 1.2.3 | E33: 11000
A34: 1.3.1 | B34: Henrique Jorge Martins Figueiredo | C34: Infraestrutura tecnológica | D34: 1.3.2 | E34: 3200
A35: 1.3.2 | B35: Henrique Jorge Martins Figueiredo | C35: Definição das datas | D35: 1.4.1 | E35: 2500
A36: 2.1 | B36: Cássio Gonçalves Gama | C36: Definição das regras dos planos (Básico, Pro e Premium) | D36: 2.1.1 | E36: 2500
A37: 2.2 | B37: Cássio Gonçalves Gama | C37: Mapeamento de fontes | D37: 2.2.1 | E37: 1250
A38: 2.2.1 | B38: Cássio Gonçalves Gama | C38: Seleção de bases do IBGE, INMET, Segurança pública e receita federal (CNPJ) | D38: 2.2.2 | E38: 1250
A39: 2.3 | B39: Time Técnico | C39: Especificação dos processos de coleta | D39: 2.3.1 | E39: 2500
A40: 2.3.1 | B40: Time Técnico | C40: Limpeza | D40: 2.3.2 | E40: 3000
... A47: 4.3 | B47: Time Técnico | C47: UrbanGrowth: Modelagem estatística de séries temporais para previsões | D47: 4.3.3 | E47: 3500
C48: UrbanRisk: Modelo de avaliação de risco territoriais | D48: 4.3.2 | E48: 3500
C49: UrbanScore: Algoritmo de potencial econônomico (0-100) | D49: 4.3.1 | E49: 3500
A50: 4.4 | B50: Time Técnico | C50: Sistema de exportação de dados | D50: 4.4.1 | E50: 500
C51: Visualização de graficos | D51: 4.4.2 | E51: 500
A52: 5.1 | B52: Time Técnico | C52: Implementação de autenticação, logs e proteção | D52: 5.1.1 | E52: 500
A53: 5.2 | B53: Time Técnico | C53: Validação das funções essenciais | D53: 5.2.1 | E53: 1000
A54: 5.2.1 | B54: Time Técnico | C54: Correção de bugs | D54: 5.2.2 | E54: 500
A55: 5.3 | B55: Time Técnico | C55: Configuração do ambiente de produção em nuvem de baixo custo | D55: 5.3.1 | E55: 1500
A56: 5.4 | B56: Henrique Figueiredo | C56: Encerramento da fase de desenvolvimento do MVP | D56: 5.4.1 | E56: 500
A57: 6.1 | B57: Cássio Gonçalves Gama | C57: Validação final dos algoritmos UrbanScore, UrbanRisk e UrbanGrowth com dados reais. | D57: 6.1.1 | E57: 6900
A58: 6.2 | B58: Renan Damprelli Cardoso da Silva | C58: Implementação de melhorias rápidas na interface após rodada de testes de usabilidade. | D58: 6.2.1 | E58: 6000
A59: 6.3 | B59: Henrique Jorge Martins Figueiredo | C59: Deploy final da aplicação web em infraestrutura de nuvem de baixo custo | D59: 6.5.1 | E59: 500
C60: Elaboração de guias de uso da plataforma e documentação da arquitetura do banco de dados. | D60: 6.3.1 | E60: 5000
A61: 6.4 | B61: Pedro Augusto da Silva Macedo | C61: Ativação das regras de negócio e controle de uso para os planos Básico, Pro e Premium | D61: 6.4.1 | E61: 9500
A62: 6.5.1 | B62: - | C62: Formalização da entrega da versão funcional (MVP) dentro do prazo estabelecido (27/05/2026) | D62: 6.6.1 | E62: 0
A63: (vazio) | B63: (vazio) | C63: Arquitetura e desenvolvimento técnico | D63: 4 | E63: 18500
C64: Design e experiência do usuário (UX/UI) | D64: 3 | E64: 14500
C65: Finalização e Entrega do MVP | D65: 6 | E65: 4000
C66: Iniciação e planejamento | D66: 1
C67: Levantamento de Requisitos e Dados | D67: 2 | E67: 30000
C68: Qualidade, segurança e lançamento | D68: 5 | E68: 15000
A69: Total Geral | E69: 301300

Sheet Cronograma_de_Custos (2)
B2: 5.2. CRONOGRAMA DE CUSTOS
B5: Ref | C5: Etapas – Atividades - Marcos
D6: 1 | E6: 2 | F6: 3 | G6: 4 | H6: 5 | I6: 6 | J6: 7 | K6: 8 | L6: 9 | M6: 10 | N6: 11 | O6: 12 | P6: 13 | Q6: 14 | R6: 15 | S6: 16 | T6: 17 | U6: 18 | V6: 19 | W6: 20 | X6: 21 | Y6: 22 | Z6: 23 | AA6: 24
D7: Agosto | H7: Setembro | L7: Outubro | P7: Novembro | T7: Dezembro | X7: Janeiro
B8: 1.1 | C8: Plano do Projeto | D8: 30000
B9: 1.2 | C9: Controle | H9: 5000 | L9: 5000 | P9: 5000 | T9: 5000
B10: 1.3 | C10: Fechamento | X10: 10000
B11: 2 | C11: Adequar o Espaço Físico | L11: 20000 | P11: 40000 | T11: 10000 | X11: 10000
B12: 3.1 | C12: Equipamentos de Ginástica | H12: 10000 | L12: 25000 | P12: 25000 | T12: 25000 | X12: 5000
B13: 3.2 | C13: Equipamentos de Apoio e Administração | L13: 15000 | P13: 15000 | T13: 20000 | X13: 10000
B14: 4 | C14: Contratar Mão de Obra | X14: 7000
B15: 5.1 | C15: Contratar empresa para informatização da academia | T15: 4000 | X15: 4000
B16: 5.2 | C16: Adquirir Sistemas de Segurança | T16: 2500 | X16: 2500
B17: 5.3 | C17: Fechar Convênio com Estacionamento próximo ao local | X17: 0
B18: 5.4 | C18: Contratação de Designer de Interiores | H18: =20000*35% -> 7000 | L18: =13000/4 -> 3250 | P18: =13000/4 -> 3250 | T18: =13000/4 -> 3250 | X18: =13000/4 -> 3250
